{"metadata": {"url": "https://minecraft.fandom.com/wiki/0.13", "title": "0.13", "time": "17/04/2022 05:55:28"}, "tables": [], "images": [{"src": "https://static.wikia.nocookie.net/minecraft_gamepedia/images/f/fd/Disambig_color.svg", "path": "images/Disambig color.png", "alt_text": "Disambig color", "caption": null, "bbox": [216.046875, 1226.875, 20, 15]}], "sprites": [], "texts": [{"text": "0.13", "bbox": [202.046875, 349.5, 593, 45]}, {"text": "\u2190 0.12 | 0.13 | 0.14 \u2192", "bbox": [202.046875, 414.5, 726, 25]}, {"text": "0.13 may refer to:", "bbox": [202.046875, 463, 726, 24]}, {"text": "Contents", "bbox": [215.046875, 527.25, 81, 17]}, {"text": "1 Java Edition\n1.1 Classic\n2 Pocket Edition\n2.1 Alpha\n3 Minecraft Earth", "bbox": [203.046875, 560.515625, 150, 161]}, {"text": "Java Edition", "bbox": [202.046875, 746.015625, 726, 43]}, {"text": "Classic", "bbox": [202.046875, 813.015625, 726, 22]}, {"text": "Java Edition Classic 0.0.13a\nJava Edition Classic 0.0.13a_03", "bbox": [238.046875, 847.515625, 690, 55]}, {"text": "Pocket Edition", "bbox": [202.046875, 926.515625, 726, 43]}, {"text": "Alpha", "bbox": [202.046875, 993.515625, 726, 23]}, {"text": "Pocket Edition v0.13.0 alpha\nPocket Edition v0.13.1 alpha\nPocket Edition v0.13.2 alpha", "bbox": [238.046875, 1028.015625, 690, 73]}, {"text": "Minecraft Earth", "bbox": [202.046875, 1119.515625, 726, 43]}, {"text": "Minecraft Earth 0.13.0", "bbox": [238.046875, 1171.515625, 690, 25]}]}