{"metadata": {"url": "https://minecraft.fandom.com/wiki/Java_Edition_pre-Classic_rd-20090515", "title": "Java_Edition_pre-Classic_rd-20090515", "time": "17/04/2022 05:20:42"}, "tables": [{"bbox": [624.9375, 1027.84375, 300, 126], "headers": {"text": ["Edition", "Release date", "Downloads"], "bboxes": [[625.9375, 1028.84375, 155, 30], [625.9375, 1059.875, 155, 30], [625.9375, 1090.90625, 155, 30]]}, "cells": {"text": ["Java Edition", "May 15, 2009", "Unavailable", "\u25c4 rd-132328 rd-160052 \u25ba"], "bboxes": [[782.234375, 1028.84375, 142, 30], [782.234375, 1059.875, 142, 30], [782.234375, 1090.90625, 142, 30], [625.9375, 1121.9375, 298, 30]]}}, {"bbox": [202.046875, 3772.390625, 726, 597], "headers": {"text": ["[hide]\nMinecraft: Java Edition versions", "Particular versions", "Development cycle", "Other updates", "Joke updates", "[hide]\nPre-Classic", "Cave Game", "Minecraft: Order of the Stone", "Minecraft", "Minecraft Alpha", "[show]\nClassic", "[show]\nIndev", "[show]\nInfdev", "[show]\nAlpha", "[show]\nBeta", "[show]\nFull Release"], "bboxes": [[205.046875, 3775.390625, 720, 27], [205.046875, 3804.34375, 171, 49], [205.046875, 3855.34375, 171, 49], [205.046875, 3906.34375, 171, 49], [205.046875, 3957.34375, 171, 74], [205.046875, 4032.84375, 720, 27], [205.046875, 4088.296875, 244, 25], [205.046875, 4114.796875, 244, 25], [205.046875, 4141.296875, 244, 25], [205.046875, 4167.796875, 244, 25], [205.046875, 4194.296875, 720, 27], [205.046875, 4223.25, 720, 27], [205.046875, 4252.203125, 720, 27], [205.046875, 4281.15625, 720, 27], [205.046875, 4310.109375, 720, 27], [205.046875, 4339.0625, 720, 27]]}, "cells": {"text": ["Demo Locations PC Gamer demo (Beta 1.3) Classic remake (0.0.23a_01) Developer versions Missing versions (Launcher)", "Pre-Classic (2009) Classic (2009) Indev (2009\u201310) Infdev (2010) Alpha (2010) Beta (2010\u201311) Full Release (2011\u2013present)", "Launcher updates Beta Sound Update (2011) Music Update (2013) Texture Update (2019)", "2.0 (2013) 15w14a (2015) 1.RV-Pre1 (2016) 3D Shareware v1.34 (2019) 20w14\u221e (2020)\n22w13oneBlockAtATime (2022)", "[hide]\nPre-Classic\nVersion history\nCave Game rd-131648 rd-131655 rd-132211 rd-132328\nMinecraft: Order of the Stone rd-20090515\nMinecraft rd-160052 rd-161348\nMinecraft Alpha mc-161607 mc-161616 mc-161625 mc-161648", "Version history", "rd-131648 rd-131655 rd-132211 rd-132328", "rd-20090515", "rd-160052 rd-161348", "mc-161607 mc-161616 mc-161625 mc-161648", "[show]\nClassic", "[show]\nIndev", "[show]\nInfdev", "[show]\nAlpha", "[show]\nBeta", "[show]\nFull Release"], "bboxes": [[378.046875, 3804.34375, 547, 49], [378.046875, 3855.34375, 547, 49], [378.046875, 3906.34375, 547, 49], [378.046875, 3957.34375, 547, 74], [205.046875, 4032.84375, 720, 159], [205.046875, 4061.796875, 720, 25], [451.046875, 4088.296875, 474, 25], [451.046875, 4114.796875, 474, 25], [451.046875, 4141.296875, 474, 25], [451.046875, 4167.796875, 474, 25], [205.046875, 4194.296875, 720, 27], [205.046875, 4223.25, 720, 27], [205.046875, 4252.203125, 720, 27], [205.046875, 4281.15625, 720, 27], [205.046875, 4310.109375, 720, 27], [205.046875, 4339.0625, 720, 27]]}}, {"bbox": [203.046875, 4030.84375, 724, 163], "headers": {"text": ["[hide]\nPre-Classic", "Cave Game", "Minecraft: Order of the Stone", "Minecraft", "Minecraft Alpha"], "bboxes": [[205.046875, 4032.84375, 720, 27], [205.046875, 4088.296875, 244, 25], [205.046875, 4114.796875, 244, 25], [205.046875, 4141.296875, 244, 25], [205.046875, 4167.796875, 244, 25]]}, "cells": {"text": ["Version history", "rd-131648 rd-131655 rd-132211 rd-132328", "rd-20090515", "rd-160052 rd-161348", "mc-161607 mc-161616 mc-161625 mc-161648"], "bboxes": [[205.046875, 4061.796875, 720, 25], [451.046875, 4088.296875, 474, 25], [451.046875, 4114.796875, 474, 25], [451.046875, 4141.296875, 474, 25], [451.046875, 4167.796875, 474, 25]]}}, {"bbox": [203.046875, 4192.296875, 724, 31], "headers": {"text": ["[show]\nClassic"], "bboxes": [[205.046875, 4194.296875, 720, 27]]}, "cells": {"text": [], "bboxes": []}}, {"bbox": [203.046875, 4221.25, 724, 31], "headers": {"text": ["[show]\nIndev"], "bboxes": [[205.046875, 4223.25, 720, 27]]}, "cells": {"text": [], "bboxes": []}}, {"bbox": [203.046875, 4250.203125, 724, 31], "headers": {"text": ["[show]\nInfdev"], "bboxes": [[205.046875, 4252.203125, 720, 27]]}, "cells": {"text": [], "bboxes": []}}, {"bbox": [203.046875, 4279.15625, 724, 31], "headers": {"text": ["[show]\nAlpha"], "bboxes": [[205.046875, 4281.15625, 720, 27]]}, "cells": {"text": [], "bboxes": []}}, {"bbox": [203.046875, 4308.109375, 724, 31], "headers": {"text": ["[show]\nBeta"], "bboxes": [[205.046875, 4310.109375, 720, 27]]}, "cells": {"text": [], "bboxes": []}}, {"bbox": [203.046875, 4337.0625, 724, 31], "headers": {"text": ["[show]\nFull Release"], "bboxes": [[205.046875, 4339.0625, 720, 27]]}, "cells": {"text": [], "bboxes": []}}], "images": [{"src": "https://static.wikia.nocookie.net/minecraft_gamepedia/images/3/3d/Missing_Model_JE3.png", "path": "images/Missing Model JE3.png", "alt_text": "Missing Model JE3", "caption": null, "bbox": [260.53125, 561.84375, 32, 32]}, {"src": "https://static.wikia.nocookie.net/minecraft_gamepedia/images/7/74/Crying_Obsidian_Programmer_Art.png", "path": "images/Crying Obsidian Programmer Art.png", "alt_text": "Crying Obsidian Programmer Art", "caption": null, "bbox": [260.53125, 708.78125, 32, 32]}, {"src": "https://static.wikia.nocookie.net/minecraft_gamepedia/images/9/90/Pre-classic_rd-20090515.jpg", "path": "images/Pre-classic rd-20090515.jpg", "alt_text": "Pre-classic rd-20090515", "caption": null, "bbox": [634.9375, 813.84375, 280, 210]}, {"src": "https://static.wikia.nocookie.net/minecraft_gamepedia/images/7/76/Dirt_JE1_BE1.png", "path": "images/Dirt JE1 BE1.png", "alt_text": "Dirt JE1 BE1", "caption": null, "bbox": [202.046875, 1368.890625, 32, 32]}, {"src": "https://static.wikia.nocookie.net/minecraft_gamepedia/images/f/f4/Cobblestone_JE1.png", "path": "images/Cobblestone JE1.png", "alt_text": "Cobblestone JE1", "caption": null, "bbox": [202.046875, 1498.390625, 32, 32]}, {"src": "https://static.wikia.nocookie.net/minecraft_gamepedia/images/7/76/Dirt_JE1_BE1.png", "path": "images/img.png", "alt_text": "", "caption": null, "bbox": [255.046875, 3246.890625, 120, 120]}, {"src": "https://static.wikia.nocookie.net/minecraft_gamepedia/images/2/29/Stone_JE2_BE1.png", "path": "images/img (1).png", "alt_text": "", "caption": null, "bbox": [413.046875, 3246.890625, 120, 120]}, {"src": "https://static.wikia.nocookie.net/minecraft_gamepedia/images/f/f0/Oak_Planks_JE1.png", "path": "images/img (2).png", "alt_text": "", "caption": null, "bbox": [571.046875, 3246.890625, 120, 120]}, {"src": "https://static.wikia.nocookie.net/minecraft_gamepedia/images/1/12/Grass_Block_JE2.png", "path": "images/img (3).png", "alt_text": "", "caption": null, "bbox": [729.046875, 3246.890625, 120, 120]}, {"src": "https://static.wikia.nocookie.net/minecraft_gamepedia/images/f/f4/Cobblestone_JE1.png", "path": "images/img (4).png", "alt_text": "", "caption": null, "bbox": [255.046875, 3440.890625, 120, 120]}, {"src": "https://static.wikia.nocookie.net/minecraft_gamepedia/images/3/34/Oak_Door_%28item%29_JE1.png", "path": "images/Oak Door (item) JE1.png", "alt_text": "Oak Door (item) JE1", "caption": null, "bbox": [761.046875, 3859.34375, 16, 16]}, {"src": "https://static.wikia.nocookie.net/minecraft_gamepedia/images/3/34/Oak_Door_%28item%29_JE1.png", "path": "images/Oak Door (item) JE1 (1).png", "alt_text": "Oak Door (item) JE1", "caption": null, "bbox": [502.390625, 4258.203125, 16, 16]}], "sprites": [{"text": null, "bbox": [215.046875, 3870.59375, 16, 16]}, {"text": null, "bbox": [380.046875, 3858.34375, 16, 16]}, {"text": null, "bbox": [523.046875, 3858.34375, 16, 16]}, {"text": null, "bbox": [637.046875, 3858.34375, 16, 16]}, {"text": null, "bbox": [869.046875, 3858.34375, 16, 16]}, {"text": "Beta", "bbox": [465.046875, 3882.84375, 16, 16]}, {"text": "Full Release", "bbox": [580.40625, 3882.84375, 16, 16]}, {"text": null, "bbox": [246.046875, 3921.59375, 16, 16]}, {"text": null, "bbox": [252.046875, 3984.84375, 16, 16]}, {"text": null, "bbox": [380.046875, 3960.34375, 16, 16]}, {"text": null, "bbox": [396.046875, 3960.34375, 16, 16]}, {"text": null, "bbox": [412.046875, 3960.34375, 16, 16]}, {"text": null, "bbox": [500.046875, 3960.34375, 16, 16]}, {"text": null, "bbox": [615.046875, 3960.34375, 16, 16]}, {"text": null, "bbox": [744.046875, 3960.34375, 16, 16]}, {"text": null, "bbox": [425.046875, 3984.84375, 16, 16]}, {"text": null, "bbox": [380.046875, 4009.34375, 16, 16]}, {"text": "Pre-Classic", "bbox": [482.5, 4036.84375, 16, 16]}, {"text": "Version history", "bbox": [507.3125, 4064.796875, 16, 16]}, {"text": null, "bbox": [342.046875, 4091.296875, 16, 16]}, {"text": null, "bbox": [215.046875, 4117.796875, 16, 16]}, {"text": null, "bbox": [351.046875, 4144.296875, 16, 16]}, {"text": null, "bbox": [307.046875, 4170.796875, 16, 16]}, {"text": "Classic", "bbox": [499, 4198.296875, 16, 16]}, {"text": null, "bbox": [505.890625, 4227.25, 16, 16]}, {"text": null, "bbox": [505.390625, 4285.15625, 16, 16]}, {"text": "Beta", "bbox": [508.5, 4314.109375, 16, 16]}, {"text": "Full Release", "bbox": [481, 4343.0625, 16, 16]}], "texts": [{"text": "Java Edition pre-Classic rd-20090515", "bbox": [202.046875, 349.5, 593, 90]}, {"text": "rd-20090515 is a pre-Classic version made on May 15, 2009.[1] This version was never released. Although there is a version titled \"rd-20090515\" in the launcher, attempting to play it downloads rd-161348 instead.", "bbox": [202.046875, 768.375, 726, 98]}, {"text": "Contents", "bbox": [215.046875, 906.125, 81, 17]}, {"text": "1 Additions\n1.1 Blocks\n1.2 General\n2 Changes\n2.1 Blocks\n2.2 Mobs\n2.3 General\n3 Trivia\n4 Gallery\n5 References", "bbox": [203.046875, 939.390625, 145, 303]}, {"text": "Additions", "bbox": [202.046875, 1267.390625, 726, 43]}, {"text": "Blocks", "bbox": [202.046875, 1334.390625, 726, 22]}, {"text": "Dirt", "bbox": [202.046875, 1368.890625, 726, 32]}, {"text": "New block.\nGenerated from Grass Blocks.\nTransforms to grass when is next to a Grass Block.", "bbox": [238.046875, 1406.890625, 690, 74]}, {"text": "Cobblestone", "bbox": [202.046875, 1498.390625, 726, 32]}, {"text": "Has a slightly modified texture of the previous texture for Stone.", "bbox": [238.046875, 1536.390625, 690, 24]}, {"text": "Planks", "bbox": [202.046875, 1578.890625, 726, 25]}, {"text": "New wood-like block.", "bbox": [238.046875, 1609.390625, 690, 24]}, {"text": "General", "bbox": [202.046875, 1657.890625, 726, 23]}, {"text": "Miscellaneous", "bbox": [202.046875, 1692.390625, 726, 24]}, {"text": "Spawn Human mobs by pressing G.[2]\nBlock picking using the number keys 1\u20134.\nSupport for different block types and dynamic blocks.\nFullscreen mode.\nCrosshair (+)\nIn this version, it was very thin.\nA thin layer of fog can now be seen in the distance of lit block surfaces.\nThe currently selected building block will now display in the top-right corner of the screen.", "bbox": [238.046875, 1722.890625, 690, 220]}, {"text": "Changes", "bbox": [202.046875, 1966.890625, 726, 43]}, {"text": "Blocks", "bbox": [202.046875, 2033.890625, 726, 23]}, {"text": "Grass Block", "bbox": [202.046875, 2068.390625, 726, 24]}, {"text": "Top Texture is slightly brighter.\nGrass Blocks now have side and bottom textures, rather than the same texture on each side.\nGrass exists on dirt while under light.[2]\nGrass blocks revert to dirt over time when they have no light.[2]\nGrass blocks revert to dirt when a block is on top of it.\nRemoved the ability to place Grass Blocks legitimately.", "bbox": [238.046875, 2098.890625, 690, 171]}, {"text": "Stone", "bbox": [202.046875, 2287.890625, 726, 25]}, {"text": "New Texture, old texture was recycled and modified for Cobblestone.", "bbox": [238.046875, 2318.390625, 690, 24]}, {"text": "Mobs", "bbox": [202.046875, 2366.890625, 726, 23]}, {"text": "Human", "bbox": [202.046875, 2401.390625, 726, 24]}, {"text": "Reduced the number of humans who spawn from 100 to 10.\nHumans who fall below level Y=-100 are now removed from the world.\nHumans now appear darker when in shade.[2]", "bbox": [238.046875, 2431.890625, 690, 74]}, {"text": "Player", "bbox": [202.046875, 2523.390625, 726, 24]}, {"text": "Changed Player's physics. Now they can jump farther, walk and fall faster.", "bbox": [238.046875, 2553.890625, 690, 25]}, {"text": "General", "bbox": [202.046875, 2602.390625, 726, 22]}, {"text": "Physics", "bbox": [202.046875, 2636.890625, 726, 25]}, {"text": "Shadows have been brightened.", "bbox": [238.046875, 2667.390625, 690, 24]}, {"text": "Level generation", "bbox": [202.046875, 2709.890625, 726, 25]}, {"text": "Unless a level.dat from an older version is launched, the world is no longer flat.\nLoading a world from older pre-Classic versions causes all blocks to become stone.", "bbox": [238.046875, 2740.390625, 690, 49]}, {"text": "Movement", "bbox": [202.046875, 2807.390625, 726, 24]}, {"text": "Moving is much slower when in midair.", "bbox": [238.046875, 2837.890625, 690, 25]}, {"text": "Trivia", "bbox": [202.046875, 2880.390625, 726, 43]}, {"text": "This version is the version shown in the \"Minecraft progress.\" video.\nUnlike other pre-classic versions, this does not use a \"ddhhmm\" (day-hour-minute) format, but instead a \"yyyymmdd\" (year-month-day) format.\nThe game was renamed from \"Cave Game\" to \"Minecraft: Order of the Stone\" prior to this version.[3]\nThe \"rd\" before the version number stands for RubyDung, a game Notch was working on before Minecraft, whose codebase was later reused for Minecraft.\nThere was a version in the launcher titled \"rd-20090515\", however, rd-20090515 is not on the Minecraft download servers, as attempting to download it will download rd-161348 instead, a much later version.\nThis is first version has been duplicated in the launcher.", "bbox": [238.046875, 2932.390625, 690, 220]}, {"text": "Gallery", "bbox": [202.046875, 3170.890625, 726, 43]}, {"text": "Dirt block\nStone block\nWood planks\nSecond Grass Block texture\nFirst Cobblestone texture", "bbox": [238.046875, 3222.890625, 690, 374]}, {"text": "Dirt block", "bbox": [240.046875, 3382.890625, 155, 18]}, {"text": "Stone block", "bbox": [398.046875, 3382.890625, 155, 18]}, {"text": "Wood planks", "bbox": [556.046875, 3382.890625, 155, 18]}, {"text": "Second Grass Block texture", "bbox": [714.046875, 3382.890625, 155, 36]}, {"text": "First Cobblestone texture", "bbox": [240.046875, 3576.890625, 155, 18]}, {"text": "References", "bbox": [202.046875, 3614.890625, 726, 43]}, {"text": "\"rd-20090515.json\" , May 15, 2009.", "bbox": [248.046875, 3669.890625, 221, 17]}, {"text": "\"Minecraft progress\" by Nizzotch. May 15, 2009. Archived from the original on April 16, 2018.", "bbox": [284.046875, 3694.390625, 580, 17]}, {"text": "\"Minecraft: Order of the Stone\" (archived) \u2013 The Word of Notch, May 14, 2009.", "bbox": [248.046875, 3718.890625, 479, 17]}]}