{"metadata": {"url": "https://minecraft.fandom.com/wiki/Pocket_Edition_v0.14.0_alpha", "title": "Pocket_Edition_v0.14.0_alpha", "time": "16/04/2022 22:48:44"}, "tables": [{"bbox": [624.9375, 626.359375, 300, 329], "headers": {"text": ["Edition", "Official name", "Internal version", "Release date", "Development versions", "Protocol version"], "bboxes": [[625.9375, 627.359375, 178, 30], [625.9375, 658.390625, 178, 52], [625.9375, 711.453125, 178, 74], [625.9375, 786.546875, 178, 30], [625.9375, 817.578125, 178, 52], [625.9375, 870.640625, 178, 30]]}, "cells": {"text": ["Pocket Edition", "Overworld Update[1]", "0.14.0.9\nWindows 10 0.140.1.0", "February 18, 2016", "Builds (7)\n(View all)", "45", "\u25c4\u25c4 v0.13.0 alpha\u25c4 v0.13.2 alpha v0.14.1 alpha \u25ba v0.15.0 alpha \u25ba\u25ba"], "bboxes": [[804.921875, 627.359375, 119, 30], [804.921875, 658.390625, 119, 52], [804.921875, 711.453125, 119, 74], [804.921875, 786.546875, 119, 30], [804.921875, 817.578125, 119, 52], [804.921875, 870.640625, 119, 30], [625.9375, 901.671875, 298, 52]]}}, {"bbox": [202.046875, 9806.90625, 726, 1065], "headers": {"text": ["[hide]\nMinecraft: Bedrock Edition versions", "Versions", "Development cycle", "Asset updates", "[hide]\nAlpha", "Pre-release", "0.1", "0.2", "0.3", "0.4", "0.5", "0.6", "0.7", "v0.7.0", "0.8", "v0.8.0", "0.9", "v0.9.0", "0.10", "v0.10.0", "0.11", "v0.11.0", "0.12", "v0.12.1", "0.13", "v0.13.0", "0.14\nOverworld Update", "v0.14.0", "0.15\nFriendly Update", "v0.15.0", "Realms", "v0.15.1", "0.16\nBoss Update", "v0.16.0", "[show]\nFull Release"], "bboxes": [[205.046875, 9809.90625, 720, 27], [205.046875, 9838.859375, 171, 25], [205.046875, 9865.359375, 171, 25], [205.046875, 9891.859375, 171, 25], [205.046875, 9918.359375, 720, 27], [205.046875, 9973.8125, 123, 25], [205.046875, 10000.3125, 123, 25], [205.046875, 10026.8125, 123, 25], [205.046875, 10053.3125, 123, 25], [205.046875, 10079.8125, 123, 25], [205.046875, 10106.3125, 123, 25], [205.046875, 10132.8125, 123, 25], [205.046875, 10159.3125, 123, 51], [330.046875, 10159.3125, 63, 25], [205.046875, 10212.3125, 123, 51], [330.046875, 10212.3125, 66, 25], [205.046875, 10265.3125, 123, 76], [330.046875, 10265.3125, 63, 49], [205.046875, 10342.8125, 123, 51], [330.046875, 10342.8125, 72, 25], [205.046875, 10395.8125, 123, 76], [330.046875, 10395.8125, 69, 49], [205.046875, 10473.3125, 123, 102], [330.046875, 10499.8125, 67, 49], [205.046875, 10577.3125, 123, 51], [330.046875, 10577.3125, 71, 25], [205.046875, 10630.3125, 123, 51], [330.046875, 10630.3125, 72, 25], [205.046875, 10683.3125, 123, 104], [330.046875, 10683.3125, 71, 51], [403.046875, 10683.3125, 71, 25], [330.046875, 10736.3125, 71, 25], [205.046875, 10789.3125, 123, 51], [330.046875, 10789.3125, 71, 25], [205.046875, 10842.3125, 720, 27]]}, "cells": {"text": ["Alpha Demo", "Alpha (2011\u201316) Full Release (2016\u2013present) Bedrock Edition (2017\u2013present)", "Texture Update (2019)", "[hide]\nAlpha\nVersion history Development versions\nPre-release Demo\n0.1 v0.1.0 v0.1.1 j v0.1.2 j v0.1.3 j\n0.2 v0.2.0 j v0.2.1 2 v0.2.2\n0.3 v0.3.0 v0.3.2 v0.3.3\n0.4 v0.4.0 j rev 2 rev 3\n0.5 v0.5.0 j\n0.6 v0.6.0 v0.6.1\n0.7\nv0.7.0 v0.6.2\nv0.7.1 v0.7.2 v0.7.3 v0.7.4 v0.7.5 v0.7.6\n0.8\nv0.8.0 build 1 build 2 build 3 build 4 build 5 build 6 build 7 build 8\nv0.8.1 v0.8.2\n0.9\nv0.9.0 build 1 build 2 build 3 build 4 build 5 build 6 build 7 build 8 build 9 (RC1) build 10 (RC2) build 11 (RC3) build 12 (RC4)\nv0.9.1 v0.9.2 v0.9.3 v0.9.4 v0.9.5\n0.10\nv0.10.0 build 1 build 2 build 3 build 4 build 5 build 6 build 7 build 8 build 9\nv0.10.1 v0.10.2 v0.10.3 v0.10.4 v0.10.5\n0.11\nv0.11.0 build 1 build 2 build 3 build 4 build 5 build 6 build 7 build 8 build 9 build 10 build 11 build 12 build 13 build 14 (RC)\nv0.11.1 v0.11.2\n0.12 v0.12.0 v0.12.0.1\nv0.12.1 build 1 build 2 build 3 build 4 build 5 build 6 build 7 build 8 build 9 build 10 build 11 build 12 build 13\nv0.12.2 v0.12.3\n0.13\nv0.13.0 build 1 build 2 build 3 build 4 build 5\nv0.13.1 v0.13.2\n0.14\nOverworld Update\nv0.14.0 build 1 build 2 build 3 build 4 build 5 build 6 build 7\nv0.14.1 v0.14.2 v0.14.3\n0.15\nFriendly Update\nv0.15.0\nRealms build 1 build 2 build 4\nbuild 1 build 2 build 3\nv0.15.1 build 1\nv0.15.2 v0.15.3 v0.15.4 v0.15.6 v0.15.7 v0.15.8 v0.15.9 v0.15.10\n0.16\nBoss Update\nv0.16.0 build 1 build 2 build 3 build 4 build 5\nv0.16.1 v0.16.2", "Version history Development versions", "Demo", "v0.1.0 v0.1.1 j v0.1.2 j v0.1.3 j", "v0.2.0 j v0.2.1 2 v0.2.2", "v0.3.0 v0.3.2 v0.3.3", "v0.4.0 j rev 2 rev 3", "v0.5.0 j", "v0.6.0 v0.6.1", "v0.7.0 v0.6.2\nv0.7.1 v0.7.2 v0.7.3 v0.7.4 v0.7.5 v0.7.6", "v0.6.2", "v0.8.0 build 1 build 2 build 3 build 4 build 5 build 6 build 7 build 8\nv0.8.1 v0.8.2", "build 1 build 2 build 3 build 4 build 5 build 6 build 7 build 8", "v0.9.0 build 1 build 2 build 3 build 4 build 5 build 6 build 7 build 8 build 9 (RC1) build 10 (RC2) build 11 (RC3) build 12 (RC4)\nv0.9.1 v0.9.2 v0.9.3 v0.9.4 v0.9.5", "build 1 build 2 build 3 build 4 build 5 build 6 build 7 build 8 build 9 (RC1) build 10 (RC2) build 11 (RC3) build 12 (RC4)", "v0.10.0 build 1 build 2 build 3 build 4 build 5 build 6 build 7 build 8 build 9\nv0.10.1 v0.10.2 v0.10.3 v0.10.4 v0.10.5", "build 1 build 2 build 3 build 4 build 5 build 6 build 7 build 8 build 9", "v0.11.0 build 1 build 2 build 3 build 4 build 5 build 6 build 7 build 8 build 9 build 10 build 11 build 12 build 13 build 14 (RC)\nv0.11.1 v0.11.2", "build 1 build 2 build 3 build 4 build 5 build 6 build 7 build 8 build 9 build 10 build 11 build 12 build 13 build 14 (RC)", "v0.12.0 v0.12.0.1\nv0.12.1 build 1 build 2 build 3 build 4 build 5 build 6 build 7 build 8 build 9 build 10 build 11 build 12 build 13\nv0.12.2 v0.12.3", "build 1 build 2 build 3 build 4 build 5 build 6 build 7 build 8 build 9 build 10 build 11 build 12 build 13", "v0.13.0 build 1 build 2 build 3 build 4 build 5\nv0.13.1 v0.13.2", "build 1 build 2 build 3 build 4 build 5", "v0.14.0 build 1 build 2 build 3 build 4 build 5 build 6 build 7\nv0.14.1 v0.14.2 v0.14.3", "build 1 build 2 build 3 build 4 build 5 build 6 build 7", "v0.15.0\nRealms build 1 build 2 build 4\nbuild 1 build 2 build 3\nv0.15.1 build 1\nv0.15.2 v0.15.3 v0.15.4 v0.15.6 v0.15.7 v0.15.8 v0.15.9 v0.15.10", "Realms build 1 build 2 build 4\nbuild 1 build 2 build 3", "build 1 build 2 build 4", "build 1", "v0.16.0 build 1 build 2 build 3 build 4 build 5\nv0.16.1 v0.16.2", "build 1 build 2 build 3 build 4 build 5", "[show]\nFull Release"], "bboxes": [[378.046875, 9838.859375, 547, 25], [378.046875, 9865.359375, 547, 25], [378.046875, 9891.859375, 547, 25], [205.046875, 9918.359375, 720, 922], [205.046875, 9947.3125, 720, 25], [330.046875, 9973.8125, 595, 25], [330.046875, 10000.3125, 595, 25], [330.046875, 10026.8125, 595, 25], [330.046875, 10053.3125, 595, 25], [330.046875, 10079.8125, 595, 25], [330.046875, 10106.3125, 595, 25], [330.046875, 10132.8125, 595, 25], [330.046875, 10159.3125, 595, 51], [395.046875, 10159.3125, 530, 25], [330.046875, 10212.3125, 595, 51], [398.046875, 10212.3125, 527, 25], [330.046875, 10265.3125, 595, 76], [395.046875, 10265.3125, 530, 49], [330.046875, 10342.8125, 595, 51], [404.046875, 10342.8125, 521, 25], [330.046875, 10395.8125, 595, 76], [401.046875, 10395.8125, 524, 49], [330.046875, 10473.3125, 595, 102], [399.046875, 10499.8125, 526, 49], [330.046875, 10577.3125, 595, 51], [403.046875, 10577.3125, 522, 25], [330.046875, 10630.3125, 595, 51], [404.046875, 10630.3125, 521, 25], [330.046875, 10683.3125, 595, 104], [403.046875, 10683.3125, 522, 51], [476.046875, 10683.3125, 449, 25], [403.046875, 10736.3125, 522, 25], [330.046875, 10789.3125, 595, 51], [403.046875, 10789.3125, 522, 25], [205.046875, 10842.3125, 720, 27]]}}, {"bbox": [203.046875, 9916.359375, 724, 926], "headers": {"text": ["[hide]\nAlpha", "Pre-release", "0.1", "0.2", "0.3", "0.4", "0.5", "0.6", "0.7", "v0.7.0", "0.8", "v0.8.0", "0.9", "v0.9.0", "0.10", "v0.10.0", "0.11", "v0.11.0", "0.12", "v0.12.1", "0.13", "v0.13.0", "0.14\nOverworld Update", "v0.14.0", "0.15\nFriendly Update", "v0.15.0", "Realms", "v0.15.1", "0.16\nBoss Update", "v0.16.0"], "bboxes": [[205.046875, 9918.359375, 720, 27], [205.046875, 9973.8125, 123, 25], [205.046875, 10000.3125, 123, 25], [205.046875, 10026.8125, 123, 25], [205.046875, 10053.3125, 123, 25], [205.046875, 10079.8125, 123, 25], [205.046875, 10106.3125, 123, 25], [205.046875, 10132.8125, 123, 25], [205.046875, 10159.3125, 123, 51], [330.046875, 10159.3125, 63, 25], [205.046875, 10212.3125, 123, 51], [330.046875, 10212.3125, 66, 25], [205.046875, 10265.3125, 123, 76], [330.046875, 10265.3125, 63, 49], [205.046875, 10342.8125, 123, 51], [330.046875, 10342.8125, 72, 25], [205.046875, 10395.8125, 123, 76], [330.046875, 10395.8125, 69, 49], [205.046875, 10473.3125, 123, 102], [330.046875, 10499.8125, 67, 49], [205.046875, 10577.3125, 123, 51], [330.046875, 10577.3125, 71, 25], [205.046875, 10630.3125, 123, 51], [330.046875, 10630.3125, 72, 25], [205.046875, 10683.3125, 123, 104], [330.046875, 10683.3125, 71, 51], [403.046875, 10683.3125, 71, 25], [330.046875, 10736.3125, 71, 25], [205.046875, 10789.3125, 123, 51], [330.046875, 10789.3125, 71, 25]]}, "cells": {"text": ["Version history Development versions", "Demo", "v0.1.0 v0.1.1 j v0.1.2 j v0.1.3 j", "v0.2.0 j v0.2.1 2 v0.2.2", "v0.3.0 v0.3.2 v0.3.3", "v0.4.0 j rev 2 rev 3", "v0.5.0 j", "v0.6.0 v0.6.1", "v0.7.0 v0.6.2\nv0.7.1 v0.7.2 v0.7.3 v0.7.4 v0.7.5 v0.7.6", "v0.6.2", "v0.8.0 build 1 build 2 build 3 build 4 build 5 build 6 build 7 build 8\nv0.8.1 v0.8.2", "build 1 build 2 build 3 build 4 build 5 build 6 build 7 build 8", "v0.9.0 build 1 build 2 build 3 build 4 build 5 build 6 build 7 build 8 build 9 (RC1) build 10 (RC2) build 11 (RC3) build 12 (RC4)\nv0.9.1 v0.9.2 v0.9.3 v0.9.4 v0.9.5", "build 1 build 2 build 3 build 4 build 5 build 6 build 7 build 8 build 9 (RC1) build 10 (RC2) build 11 (RC3) build 12 (RC4)", "v0.10.0 build 1 build 2 build 3 build 4 build 5 build 6 build 7 build 8 build 9\nv0.10.1 v0.10.2 v0.10.3 v0.10.4 v0.10.5", "build 1 build 2 build 3 build 4 build 5 build 6 build 7 build 8 build 9", "v0.11.0 build 1 build 2 build 3 build 4 build 5 build 6 build 7 build 8 build 9 build 10 build 11 build 12 build 13 build 14 (RC)\nv0.11.1 v0.11.2", "build 1 build 2 build 3 build 4 build 5 build 6 build 7 build 8 build 9 build 10 build 11 build 12 build 13 build 14 (RC)", "v0.12.0 v0.12.0.1\nv0.12.1 build 1 build 2 build 3 build 4 build 5 build 6 build 7 build 8 build 9 build 10 build 11 build 12 build 13\nv0.12.2 v0.12.3", "build 1 build 2 build 3 build 4 build 5 build 6 build 7 build 8 build 9 build 10 build 11 build 12 build 13", "v0.13.0 build 1 build 2 build 3 build 4 build 5\nv0.13.1 v0.13.2", "build 1 build 2 build 3 build 4 build 5", "v0.14.0 build 1 build 2 build 3 build 4 build 5 build 6 build 7\nv0.14.1 v0.14.2 v0.14.3", "build 1 build 2 build 3 build 4 build 5 build 6 build 7", "v0.15.0\nRealms build 1 build 2 build 4\nbuild 1 build 2 build 3\nv0.15.1 build 1\nv0.15.2 v0.15.3 v0.15.4 v0.15.6 v0.15.7 v0.15.8 v0.15.9 v0.15.10", "Realms build 1 build 2 build 4\nbuild 1 build 2 build 3", "build 1 build 2 build 4", "build 1", "v0.16.0 build 1 build 2 build 3 build 4 build 5\nv0.16.1 v0.16.2", "build 1 build 2 build 3 build 4 build 5"], "bboxes": [[205.046875, 9947.3125, 720, 25], [330.046875, 9973.8125, 595, 25], [330.046875, 10000.3125, 595, 25], [330.046875, 10026.8125, 595, 25], [330.046875, 10053.3125, 595, 25], [330.046875, 10079.8125, 595, 25], [330.046875, 10106.3125, 595, 25], [330.046875, 10132.8125, 595, 25], [330.046875, 10159.3125, 595, 51], [395.046875, 10159.3125, 530, 25], [330.046875, 10212.3125, 595, 51], [398.046875, 10212.3125, 527, 25], [330.046875, 10265.3125, 595, 76], [395.046875, 10265.3125, 530, 49], [330.046875, 10342.8125, 595, 51], [404.046875, 10342.8125, 521, 25], [330.046875, 10395.8125, 595, 76], [401.046875, 10395.8125, 524, 49], [330.046875, 10473.3125, 595, 102], [399.046875, 10499.8125, 526, 49], [330.046875, 10577.3125, 595, 51], [403.046875, 10577.3125, 522, 25], [330.046875, 10630.3125, 595, 51], [404.046875, 10630.3125, 521, 25], [330.046875, 10683.3125, 595, 104], [403.046875, 10683.3125, 522, 51], [476.046875, 10683.3125, 449, 25], [403.046875, 10736.3125, 522, 25], [330.046875, 10789.3125, 595, 51], [403.046875, 10789.3125, 522, 25]]}}, {"bbox": [328.046875, 10157.3125, 599, 29], "headers": {"text": ["v0.7.0"], "bboxes": [[330.046875, 10159.3125, 63, 25]]}, "cells": {"text": ["v0.6.2"], "bboxes": [[395.046875, 10159.3125, 530, 25]]}}, {"bbox": [328.046875, 10210.3125, 599, 29], "headers": {"text": ["v0.8.0"], "bboxes": [[330.046875, 10212.3125, 66, 25]]}, "cells": {"text": ["build 1 build 2 build 3 build 4 build 5 build 6 build 7 build 8"], "bboxes": [[398.046875, 10212.3125, 527, 25]]}}, {"bbox": [328.046875, 10263.3125, 599, 53], "headers": {"text": ["v0.9.0"], "bboxes": [[330.046875, 10265.3125, 63, 49]]}, "cells": {"text": ["build 1 build 2 build 3 build 4 build 5 build 6 build 7 build 8 build 9 (RC1) build 10 (RC2) build 11 (RC3) build 12 (RC4)"], "bboxes": [[395.046875, 10265.3125, 530, 49]]}}, {"bbox": [328.046875, 10340.8125, 599, 29], "headers": {"text": ["v0.10.0"], "bboxes": [[330.046875, 10342.8125, 72, 25]]}, "cells": {"text": ["build 1 build 2 build 3 build 4 build 5 build 6 build 7 build 8 build 9"], "bboxes": [[404.046875, 10342.8125, 521, 25]]}}, {"bbox": [328.046875, 10393.8125, 599, 53], "headers": {"text": ["v0.11.0"], "bboxes": [[330.046875, 10395.8125, 69, 49]]}, "cells": {"text": ["build 1 build 2 build 3 build 4 build 5 build 6 build 7 build 8 build 9 build 10 build 11 build 12 build 13 build 14 (RC)"], "bboxes": [[401.046875, 10395.8125, 524, 49]]}}, {"bbox": [328.046875, 10497.8125, 599, 53], "headers": {"text": ["v0.12.1"], "bboxes": [[330.046875, 10499.8125, 67, 49]]}, "cells": {"text": ["build 1 build 2 build 3 build 4 build 5 build 6 build 7 build 8 build 9 build 10 build 11 build 12 build 13"], "bboxes": [[399.046875, 10499.8125, 526, 49]]}}, {"bbox": [328.046875, 10575.3125, 599, 29], "headers": {"text": ["v0.13.0"], "bboxes": [[330.046875, 10577.3125, 71, 25]]}, "cells": {"text": ["build 1 build 2 build 3 build 4 build 5"], "bboxes": [[403.046875, 10577.3125, 522, 25]]}}, {"bbox": [328.046875, 10628.3125, 599, 29], "headers": {"text": ["v0.14.0"], "bboxes": [[330.046875, 10630.3125, 72, 25]]}, "cells": {"text": ["build 1 build 2 build 3 build 4 build 5 build 6 build 7"], "bboxes": [[404.046875, 10630.3125, 521, 25]]}}, {"bbox": [328.046875, 10681.3125, 599, 82], "headers": {"text": ["v0.15.0", "Realms", "v0.15.1"], "bboxes": [[330.046875, 10683.3125, 71, 51], [403.046875, 10683.3125, 71, 25], [330.046875, 10736.3125, 71, 25]]}, "cells": {"text": ["Realms build 1 build 2 build 4\nbuild 1 build 2 build 3", "build 1 build 2 build 4", "build 1"], "bboxes": [[403.046875, 10683.3125, 522, 51], [476.046875, 10683.3125, 449, 25], [403.046875, 10736.3125, 522, 25]]}}, {"bbox": [401.046875, 10681.3125, 526, 29], "headers": {"text": ["Realms"], "bboxes": [[403.046875, 10683.3125, 71, 25]]}, "cells": {"text": ["build 1 build 2 build 4"], "bboxes": [[476.046875, 10683.3125, 449, 25]]}}, {"bbox": [328.046875, 10787.3125, 599, 29], "headers": {"text": ["v0.16.0"], "bboxes": [[330.046875, 10789.3125, 71, 25]]}, "cells": {"text": ["build 1 build 2 build 3 build 4 build 5"], "bboxes": [[403.046875, 10789.3125, 522, 25]]}}, {"bbox": [203.046875, 10840.3125, 724, 31], "headers": {"text": ["[show]\nFull Release"], "bboxes": [[205.046875, 10842.3125, 720, 27]]}, "cells": {"text": [], "bboxes": []}}], "images": [{"src": "https://static.wikia.nocookie.net/minecraft_gamepedia/images/1/15/Pocket_Edition_0.14.0.png", "path": "images/Pocket Edition 0.14.0.png", "alt_text": "Pocket Edition 0.14.0", "caption": null, "bbox": [634.9375, 464.359375, 280, 158]}, {"src": "https://static.wikia.nocookie.net/minecraft_gamepedia/images/a/a7/Heart.svg", "path": "images/Heart.png", "alt_text": "Heart", "caption": null, "bbox": [276.046875, 10031.171875, 16, 16]}], "sprites": [{"text": null, "bbox": [215.046875, 9868.359375, 16, 16]}, {"text": "Alpha", "bbox": [380.046875, 9869.71875, 16, 16]}, {"text": "Full Release", "bbox": [502.40625, 9868.359375, 16, 16]}, {"text": "Bedrock Edition", "bbox": [696.765625, 9868.359375, 16, 16]}, {"text": null, "bbox": [245.046875, 9894.859375, 16, 16]}, {"text": "Alpha", "bbox": [504.5, 9924.359375, 16, 16]}, {"text": "Version history", "bbox": [420.125, 9950.3125, 16, 16]}, {"text": "Development versions", "bbox": [546.484375, 9950.3125, 16, 16]}, {"text": null, "bbox": [218.046875, 9976.8125, 16, 16]}, {"text": null, "bbox": [279.046875, 10003.3125, 16, 16]}, {"text": null, "bbox": [276.046875, 10056.3125, 16, 16]}, {"text": null, "bbox": [275.046875, 10082.8125, 16, 16]}, {"text": null, "bbox": [276.046875, 10109.3125, 16, 16]}, {"text": null, "bbox": [276.046875, 10135.8125, 16, 16]}, {"text": null, "bbox": [277.046875, 10175.5625, 16, 16]}, {"text": null, "bbox": [275.046875, 10228.5625, 16, 16]}, {"text": null, "bbox": [277.046875, 10293.8125, 16, 16]}, {"text": null, "bbox": [269.046875, 10359.0625, 16, 16]}, {"text": null, "bbox": [272.046875, 10424.3125, 16, 16]}, {"text": null, "bbox": [270.046875, 10515.0625, 16, 16]}, {"text": null, "bbox": [270.046875, 10593.5625, 16, 16]}, {"text": null, "bbox": [269.046875, 10634.3125, 16, 16]}, {"text": null, "bbox": [270.046875, 10713.8125, 16, 16]}, {"text": null, "bbox": [270.046875, 10793.3125, 16, 16]}, {"text": "Full Release", "bbox": [481, 10846.3125, 16, 16]}], "texts": [{"text": "Pocket Edition v0.14.0 alpha", "bbox": [202.046875, 353.890625, 593, 45]}, {"text": "For a guide about all content in this release and the other releases of the Overworld Update, see Bedrock Edition guides/Overworld Update.", "bbox": [216.046875, 418.890625, 712, 74]}, {"text": "v0.14.0, the first release of the Overworld Update, is a major update to Minecraft: Pocket Edition that was released on February 18, 2016. It added more redstone-related blocks, witch huts, maps, slime blocks, and a redesign of some menu interfaces. The update was the first to receive a name in the history of Pocket Edition.", "bbox": [202.046875, 499.390625, 726, 147]}, {"text": "Contents", "bbox": [215.046875, 686.140625, 81, 17]}, {"text": "1 Additions\n1.1 Blocks\n1.2 Items\n1.3 Mobs\n1.4 World generation\n1.5 Gameplay\n1.6 General\n2 Changes\n2.1 Blocks\n2.2 Items\n2.3 Mobs\n2.4 World generation\n2.5 General\n3 Fixes\n4 Trivia\n5 References", "bbox": [203.046875, 719.40625, 183, 474]}, {"text": "Additions", "bbox": [202.046875, 1218.40625, 726, 43]}, {"text": "Blocks", "bbox": [202.046875, 1285.40625, 726, 22]}, {"text": "Redstone components\nComparators\nDispensers\nVersion exclusive: Custom name does not appear in GUI.\nDouble trapped chests\nDroppers\nVersion exclusive: Custom name does not appear in GUI.\nHoppers\nVersion exclusive: Custom name does not appear in GUI.\nRepeaters\nLocked Repeaters\nNew minecart variants\nMinecart with chest\nVersion exclusive: Emits smoke when destroyed.\nVersion exclusive: Custom name does not appear in GUI.\nMinecart with TNT\nVersion exclusive: Emits smoke when destroyed.\nMinecart with hopper\nVersion exclusive: Emits smoke when destroyed.\nVersion exclusive: Custom name does not appear in GUI.\nCauldrons\nVersion exclusive: Water color can be changed by adding dyes.\nVersion exclusive: Colors can be mixed.\nVersion exclusive: Can be used to dye leather armor.\nVersion exclusive: Water bottles can be used to refill water.\nVersion exclusive: Can store potions.\nVersion exclusive: Will make an explosion sound if potions are mixed, and the potions will disappear.\nVersion exclusive: Potions inside cauldrons have a bubbling effect.\nBuckets can now be filled from a full cauldron.\nRed sandstone\nRed sandstone stairs\nRed sandstone slabs\nChiseled red sandstone\nSmooth red sandstone\nSlime blocks", "bbox": [238.046875, 1319.90625, 690, 1158]}, {"text": "Items", "bbox": [202.046875, 2501.90625, 726, 23]}, {"text": "Item frames\nVersion exclusive: Uses BlockEntity instead of Entity.\nVersion exclusive: Can't be placed in blocks.\nUses new sounds.\nMaps\nVersion exclusive: Crafted using nine paper.\nVersion exclusive: Compass must be added through an anvil in order to show the player's position.\nVersion exclusive: Can be cloned using the anvil, instead of the crafting table.\nVersion exclusive: Can be zoomed using the anvil, instead of the crafting table.\nVersion exclusive: Added Camera back.\nNew texture\nNow has an interact button\nCan only be received through inventory editing.\nEnder pearls\nCan only be obtained through mods.\nSpawn eggs\nWitches", "bbox": [238.046875, 2536.40625, 690, 518]}, {"text": "Mobs", "bbox": [202.046875, 3078.90625, 726, 23]}, {"text": "Witches\nUses new sounds.\nWhen more than 11 blocks from a target and lacking swiftness, 50% chance of drinking a potion of swiftness.", "bbox": [238.046875, 3113.40625, 690, 104]}, {"text": "World generation", "bbox": [202.046875, 3241.40625, 726, 22]}, {"text": "Witch huts\nVersion exclusive: Cauldron contains random potion.", "bbox": [238.046875, 3275.90625, 690, 55]}, {"text": "Gameplay", "bbox": [202.046875, 3354.90625, 726, 23]}, {"text": "Creative mode\nAdded survival inventory tabs and crafting tabs.\nAdded the ability to put on armor in creative.\nThe player now keeps their inventory when changing a world to survival.", "bbox": [238.046875, 3389.40625, 690, 104]}, {"text": "General", "bbox": [202.046875, 3517.40625, 726, 22]}, {"text": "Replaced Pocket Edition start screen with new UI.\nAdded more Achievements. (Windows 10 Only)\nAdded Export button to pause menu. (Windows 10 Only)\nButton generates a file with suffix .mcworld.\nCan be imported using the Import button.\nAdded Import button to world selection screen (Windows 10 Only)\nWorlds can now be imported.\nCan only import worlds from files with suffix .mcworld and must have valid world files in them.\nItems now have an updated rendering system.\nSkin packs\nRedstone Specialists skin pack.\nTextures\nUpdate texture of language button.\nLooks more like Windows 10 Edition button.\nOptions\nChange GUI size option.\nNew interact buttons\nOpen\nUsed when opening minecarts with chests and minecarts with hoppers.\nCreate map\nUsed when creating maps.", "bbox": [238.046875, 3551.90625, 690, 689]}, {"text": "Changes", "bbox": [202.046875, 4264.40625, 726, 43]}, {"text": "Blocks", "bbox": [202.046875, 4331.40625, 726, 22]}, {"text": "Trapped chests\nWill now form a double trapped chest when placed next to each other.\nPumpkins and mob heads\nCan now be worn as armor by the player.\nDouble flowers\nWill now spawn their respective items when bonemealed.\nFlowers\nThe hitbox of flowers and similar is not the full block anymore.", "bbox": [238.046875, 4365.90625, 690, 274]}, {"text": "Items", "bbox": [202.046875, 4663.90625, 726, 23]}, {"text": "Leather armor\nCan now be dyed.\nBoats\nNow appear exactly where the player has clicked/tapped.\nSnowballs\nNow spawn when breaking snow with a shovel.\nSplash Water Bottle\nIt extinguishes any fire block that it's thrown at, as well as a maximum of five of them in the vicinity.", "bbox": [238.046875, 4698.40625, 690, 274]}, {"text": "Mobs", "bbox": [202.046875, 4996.40625, 726, 22]}, {"text": "Baby zombies\nVersion exclusive: Now has a 15% chance of being a jockey. If they want to be a jockey, upon nearing the player or villager, they will check for one of the following to mount before attacking:\nAdult chicken\nAdult ocelot\nAdult wolf\nAdult zombie\nCow\nPig\nSheep\nSpider\nBlazes\nVersion exclusive: Now glow in the dark.\nCreepers\nAre slightly shorter (1.7 blocks tall rather than 1.8).\nDetection range for players wearing their corresponding mob head adjusted to be 50% of the normal range.\nExplosions are now much stronger and consistent in power\nEndermen\nDrop the block they were holding when killed.\nGhasts\nVersion exclusive: Now have glowing eyes.\nMagma cubes\nVersion exclusive: Cores now glow in the dark.\nVillagers\nAre slightly taller (1.95 blocks tall rather than 1.8).\nWill now spawn a witch when struck by lightning.\nNaturally spawned villagers will now have more variety of professions\nSkeletons\nDetection range for players wearing their corresponding mob head adjusted to be 50% of the normal range.\nAre slightly taller (1.99 blocks tall rather than 1.95).\nZombies\nDetection range for players wearing their corresponding mob head adjusted to be 50% of the normal range.\nCows\nAre slightly taller (1.4 blocks tall rather than 1.3, with babies 0.7 blocks tall rather than 0.65).\nMooshrooms\nAre slightly taller (1.4 blocks tall rather than 1.3, with babies 0.7 blocks tall rather than 0.65).\nSquid\nVersion exclusive: Now have bubbling particles.\nAre slightly smaller (0.8 blocks square rather than 0.95).\nWither skeletons\nAre slightly smaller (2.4 blocks tall and 0.7 blocks wide rather than 2.535 blocks tall and 0.72 blocks wide).\nIron golems\nAre slightly shorter (2.7 blocks tall rather than 2.9).\nWolves\nAre slightly taller (0.85 blocks tall rather than 0.8).", "bbox": [238.046875, 5030.90625, 690, 1549]}, {"text": "World generation", "bbox": [202.046875, 6603.40625, 726, 22]}, {"text": "Mineshafts\nWill now generate minecarts with chests.\nVillages\nIncreased door to villager ratio in villages.\nDouble ferns\nNow spawn in cold climates all over the world.\nMoss stone boulders\nMega Taigas' moss stone boulders are rounder.\nHuge mushrooms\nNo longer spawn in the water around roofed forests.", "bbox": [238.046875, 6637.90625, 690, 347]}, {"text": "General", "bbox": [202.046875, 7008.90625, 726, 23]}, {"text": "Graphics/Performance\nCleaned up textures.\nScreenshots are full .png files.\nSnow, carpet, and slabs now render faster.\nImproved loading times.\nChanged inventory button texture.\nCreative mode\nChests, anvils, furnaces, droppers, dispensers, brewing stands, enchantment tables, hoppers and crafting tables can now be interacted with by Creative mode players.\nThe player can now pick up 64 of a block in creative by tapping and holding.\nOptions\nBroadcast to LAN is now grayed out during gameplay to indicate that it can't be changed.\nUpdated translations.", "bbox": [238.046875, 7043.40625, 690, 390]}, {"text": "Fixes", "bbox": [202.046875, 7451.90625, 726, 43]}, {"text": "79 bugs fixed", "bbox": [202.046875, 7503.90625, 726, 25]}, {"text": "Trapped chest does not provide power to redstone repeater.\nAll clay types are displayed as gray blocks on the map.\nDouble fence gates don\u2019t block users.\nPlayer is unable to open minecart with chest and minecart with hopper.\nPlayer can\u2019t close the chest window.\nCrash when a server kicks a player for inactivity.\nMechanisms are being powered by redstone dust that is not aligned with them.\nBuilding massive world structures can lead to serious performance issues.\nCrash when a farmer villager runs out of seed to plant.\nController\u2019s D-pad is inactive in the brewing stand interface.\nBackgrounds & buttons in Asian languages are too short for longer phrases.\nTNT minecart explosion on the curve does not destroy rail tracks under explosion.\nFixed most issues with chunks being sent multiple times.\nFixed server not running at the correct speed.\nAmount of hits required to kill witch doesn\u2019t vary with the weapon.\nFixed out-of-bounds error in Inventory related to linked slots.\nPlayer keeps all but armor in their inventory upon death.\nSkeleton heads don\u2019t look hollow from the bottom.\nFence gates weren\u2019t restoring their open state correctly either. The same pattern was needed as DoorBlock and TrapDoorBlock.\nCharacter's arms are in weird positions on Kindle and some iPads.\nThe player is not able to open the chest when the character stands close to it.\nItems from the bottom half of the double chest disappear when the world is restarted.\nMissing Feed button when holding any kind of meat in front of an untamed wolf.\nMissing Feed button while holding beetroot and potato in front of a pig.\nNo sound of swimming underwater.\nPlayer keeps moving after Player opens inventory screen with controller.\nSlots on anvil not lined up.\nMinecarts do not stack.\nThe terrain flickers invisible if too many chunks are updated at the same time.\nMushroom stew should not be poisonous.\nThe darkening underwater effect fails to occur if the user rides a boat into a waterfall.\nFlickering fence texture when it\u2019s put underwater.\nClay generates instead of gravel.\nIt is no longer possible to stack beetroot soup.\nCannot use colors in chat.\nMobs stay aggressive after switching back to creative.\nEnderman glitches.\nFixed door textures.\nFixed UI scaling issues.\nMCPE-369 \u2013 Animals cannot walk through open doors.\nMCPE-7947 \u2013 You cannot bonemeal 2 high plants.\nMCPE-8002 \u2013 Animals and NPCs despawn randomly.\nMCPE-9357 \u2013 Invert Y-Axis cannot be turned on when using touch controls on any platform but works as expected with controllers.\nMCPE-9378 \u2013 Auto-jump cannot be turned off when using touch controls on any platform but works as expected with controllers.\nMCPE-9555 \u2013 The rain and snow cross the blocks.\nMCPE-9803 \u2013 Korean translation error in 0.11.0 & 0.12.1.\nMCPE-9866 \u2013 Nether portal facing the ocean won't show the water.\nMCPE-10206 \u2013 \"Play\" button not translating when you selected a different language.\nMCPE-10290 \u2013 The buttons are bigger in cellphones and 7 inches tablet.\nMCPE-10507 \u2013 Tapping D-pad arrows highlights block beneath.\nMCPE-10664 \u2013 Enchantment tables hurt iron golems.\nMCPE-10868 \u2013 Killing then healing peaceful mobs brings them partially back to life.\nMCPE-11086 \u2013 All mobs drop nothing unless killed by the player (or spawned or hurt by the player within 5 min of being killed).\nMCPE-11158 \u2013 Boat doesn't travel for people on LAN.\nMCPE-11166 \u2013 Tamed Wolves display button Sit or Stand instead of Feed when holding Rotten Flesh.\nMCPE-11269 \u2013 GUI Bug (in Japanese).\nMCPE-11274 \u2013 Trapped chests do not combine to form a large trapped chest.\nMCPE-11282 \u2013 Giant mushrooms are no longer spawned in terrain generation.\nMCPE-11583 \u2013 Milking a cow causes players to drink the milk immediately.\nMCPE-11585 \u2013 Lily pads not generating in Swamp biomes.\nMCPE-11586 \u2013 Ghast attack animation does not appear when Ghasts attack.\nMCPE-11845 \u2013 Opening Menu causes the player to stop crouching or sneaking.\nMCPE-11876 \u2013 Iron golem takes damage by a cake.\nMCPE-11898 \u2013 Iron golem get hurt while standing in daylight sensor night/day.\nMCPE-11932 \u2013 Impossible redstone torch clock.\nMCPE-12081 \u2013 [0.13.1] Slim custom skin models are titled \"skins.customSlim\".\nMCPE-12091 \u2013 Dog collars cannot display colors other than white.\nMCPE-12097 \u2013 [0.13.1] Held items do not move along with the arm.\nMCPE-12102 \u2013 [0.13.1] Player's arms do not move from the idle position when aiming a bow.\nMCPE-12110 \u2013 Inconsistent opaqueness of redstone lamp.\nMCPE-12161 \u2013 Zombie Pigman hat layer is missing.\nMCPE-12165 \u2013 Mushrooms are not converted into giant mushrooms.\nMCPE-12261 \u2013 Zombie villager's left leg is z-fighting something.\nMCPE-12278 \u2013 Fences are not connected to monster spawner.\nMCPE-12330 \u2013 Mooshrooms, cows, pigs, sheep, and chickens don't panic after being attacked by the player.\nMCPE-12353 \u2013 Iron golem suffocates on non-full blocks.\nMCPE-12451 \u2013 No Achievement for Rainbow Collection.\nMCPE-12468 \u2013 Background spinning camera at the language menu does not act the same as the main menu.\nMCPE-12594 \u2013 Translation error Espa\u00f1ol (Espa\u00f1a).", "bbox": [238.046875, 7552.40625, 690, 2033]}, {"text": "Trivia", "bbox": [202.046875, 9603.90625, 726, 43]}, {"text": "This is the first Pocket Edition update to receive an official name by Mojang.", "bbox": [238.046875, 9655.90625, 690, 25]}, {"text": "References", "bbox": [202.046875, 9698.40625, 726, 43]}, {"text": "http://news.xbox.com/2016/11/11/end-2016-ender-update-minecraft-windows-10-pocket-edition/", "bbox": [248.046875, 9753.40625, 643, 17]}]}