{"metadata": {"url": "https://minecraft.fandom.com/wiki/Shrubland", "title": "Shrubland", "time": "17/04/2022 05:45:28"}, "tables": [{"bbox": [624.9375, 748.34375, 300, 170], "headers": {"text": ["Type", "Rarity", "Temperature", "Blocks"], "bboxes": [[625.9375, 749.34375, 118, 30], [625.9375, 780.375, 118, 30], [625.9375, 811.40625, 118, 30], [625.9375, 842.4375, 118, 74]]}, "cells": {"text": ["Dry", "Common - Uncommon", ">50%, <97%", "Grass Block\nLeaves\nLogs"], "bboxes": [[744.703125, 749.34375, 179, 30], [744.703125, 780.375, 179, 30], [744.703125, 811.40625, 179, 30], [744.703125, 842.4375, 179, 74]]}}, {"bbox": [202.046875, 962.875, 341, 218], "headers": {"text": ["Java Edition Alpha", "v1.2.0", "preview", "Java Edition Beta", "1.8", "Pre-release", "Legacy Console Edition", "TU1", "CU1", "1.0", "Patch 1", "", "TU5"], "bboxes": [[202.546875, 963.375, 340, 31], [202.546875, 994.46875, 79, 31], [281.921875, 994.46875, 109, 31], [202.546875, 1025.5625, 340, 31], [202.546875, 1056.65625, 79, 31], [281.921875, 1056.65625, 109, 31], [202.546875, 1087.75, 340, 31], [202.546875, 1118.84375, 40, 31], [242.734375, 1118.84375, 39, 62], [281.921875, 1118.84375, 33, 62], [315.109375, 1118.84375, 64, 62], [379.296875, 1118.84375, 12, 62], [202.546875, 1149.9375, 40, 31]]}, "cells": {"text": ["Added shrublands.", "Removed shrublands.", "Added shrublands.", "Removed shrublands."], "bboxes": [[391.484375, 994.46875, 152, 31], [391.484375, 1056.65625, 152, 31], [391.484375, 1118.84375, 152, 31], [391.484375, 1149.9375, 152, 31]]}}], "images": [{"src": "https://static.wikia.nocookie.net/minecraft_gamepedia/images/e/e7/Dark_Oak_Sapling_JE7_BE2.png", "path": "images/Dark Oak Sapling JE7 BE2.png", "alt_text": "Dark Oak Sapling JE7 BE2", "caption": null, "bbox": [260.53125, 431.09375, 32, 32]}, {"src": "https://static.wikia.nocookie.net/minecraft_gamepedia/images/b/bf/Shrubland.jpg", "path": "images/Shrubland.jpg", "alt_text": "Shrubland", "caption": null, "bbox": [649.9375, 597.34375, 250, 147]}], "sprites": [{"text": null, "bbox": [260.53125, 492.28125, 32, 32]}, {"text": null, "bbox": [725.4375, 564.875, 16, 16]}, {"text": "Grass Block", "bbox": [748.703125, 849.4375, 16, 16]}, {"text": "Leaves", "bbox": [748.703125, 871.46875, 16, 16]}, {"text": "Logs", "bbox": [748.703125, 893.5, 16, 16]}], "texts": [{"text": "Shrubland", "bbox": [202.046875, 349.5, 593, 45]}, {"text": "Shrublands were a biome, which existed in the game prior to the Adventure Update. they were usually quite flat due to height variation decreasing at lower rainfalls. In the Beta 1.8 Adventure Update they were removed from the game.", "bbox": [202.046875, 551.875, 726, 98]}, {"text": "Description", "bbox": [202.046875, 673.875, 407, 43]}, {"text": "A biome with few trees and no tall grass. It is identical to the savanna biome. Along with swampland, it was one of the smallest biomes in the game, rarely ever being larger than a few chunks, and only spawns if the temperature is between 50% and 97%, and the rainfall value is below 35% and therefore too little to generate a forest. So, they were pretty useless.", "bbox": [202.046875, 725.875, 726, 147]}, {"text": "History", "bbox": [202.046875, 896.875, 407, 43]}, {"text": "Biomes[show] [edit]", "bbox": [205.046875, 1212.53125, 720, 25]}]}