{"metadata": {"url": "https://minecraft.fandom.com/wiki/Pocket_Edition_v0.10.0_alpha/Development_versions", "title": "Pocket_Edition_v0.10.0_alpha/Development_versions", "time": "16/04/2022 23:13:18"}, "tables": [{"bbox": [202.046875, 5845.390625, 726, 1065], "headers": {"text": ["[hide]\nMinecraft: Bedrock Edition versions", "Versions", "Development cycle", "Asset updates", "[hide]\nAlpha", "Pre-release", "0.1", "0.2", "0.3", "0.4", "0.5", "0.6", "0.7", "v0.7.0", "0.8", "v0.8.0", "0.9", "v0.9.0", "0.10", "v0.10.0", "0.11", "v0.11.0", "0.12", "v0.12.1", "0.13", "v0.13.0", "0.14\nOverworld Update", "v0.14.0", "0.15\nFriendly Update", "v0.15.0", "Realms", "v0.15.1", "0.16\nBoss Update", "v0.16.0", "[show]\nFull Release"], "bboxes": [[205.046875, 5848.390625, 720, 27], [205.046875, 5877.34375, 171, 25], [205.046875, 5903.84375, 171, 25], [205.046875, 5930.34375, 171, 25], [205.046875, 5956.84375, 720, 27], [205.046875, 6012.296875, 123, 25], [205.046875, 6038.796875, 123, 25], [205.046875, 6065.296875, 123, 25], [205.046875, 6091.796875, 123, 25], [205.046875, 6118.296875, 123, 25], [205.046875, 6144.796875, 123, 25], [205.046875, 6171.296875, 123, 25], [205.046875, 6197.796875, 123, 51], [330.046875, 6197.796875, 63, 25], [205.046875, 6250.796875, 123, 51], [330.046875, 6250.796875, 66, 25], [205.046875, 6303.796875, 123, 76], [330.046875, 6303.796875, 63, 49], [205.046875, 6381.296875, 123, 51], [330.046875, 6381.296875, 72, 25], [205.046875, 6434.296875, 123, 76], [330.046875, 6434.296875, 69, 49], [205.046875, 6511.796875, 123, 102], [330.046875, 6538.296875, 67, 49], [205.046875, 6615.796875, 123, 51], [330.046875, 6615.796875, 71, 25], [205.046875, 6668.796875, 123, 51], [330.046875, 6668.796875, 72, 25], [205.046875, 6721.796875, 123, 104], [330.046875, 6721.796875, 71, 51], [403.046875, 6721.796875, 71, 25], [330.046875, 6774.796875, 71, 25], [205.046875, 6827.796875, 123, 51], [330.046875, 6827.796875, 71, 25], [205.046875, 6880.796875, 720, 27]]}, "cells": {"text": ["Alpha Demo", "Alpha (2011\u201316) Full Release (2016\u2013present) Bedrock Edition (2017\u2013present)", "Texture Update (2019)", "[hide]\nAlpha\nVersion history Development versions\nPre-release Demo\n0.1 v0.1.0 v0.1.1 j v0.1.2 j v0.1.3 j\n0.2 v0.2.0 j v0.2.1 2 v0.2.2\n0.3 v0.3.0 v0.3.2 v0.3.3\n0.4 v0.4.0 j rev 2 rev 3\n0.5 v0.5.0 j\n0.6 v0.6.0 v0.6.1\n0.7\nv0.7.0 v0.6.2\nv0.7.1 v0.7.2 v0.7.3 v0.7.4 v0.7.5 v0.7.6\n0.8\nv0.8.0 build 1 build 2 build 3 build 4 build 5 build 6 build 7 build 8\nv0.8.1 v0.8.2\n0.9\nv0.9.0 build 1 build 2 build 3 build 4 build 5 build 6 build 7 build 8 build 9 (RC1) build 10 (RC2) build 11 (RC3) build 12 (RC4)\nv0.9.1 v0.9.2 v0.9.3 v0.9.4 v0.9.5\n0.10\nv0.10.0 build 1 build 2 build 3 build 4 build 5 build 6 build 7 build 8 build 9\nv0.10.1 v0.10.2 v0.10.3 v0.10.4 v0.10.5\n0.11\nv0.11.0 build 1 build 2 build 3 build 4 build 5 build 6 build 7 build 8 build 9 build 10 build 11 build 12 build 13 build 14 (RC)\nv0.11.1 v0.11.2\n0.12 v0.12.0 v0.12.0.1\nv0.12.1 build 1 build 2 build 3 build 4 build 5 build 6 build 7 build 8 build 9 build 10 build 11 build 12 build 13\nv0.12.2 v0.12.3\n0.13\nv0.13.0 build 1 build 2 build 3 build 4 build 5\nv0.13.1 v0.13.2\n0.14\nOverworld Update\nv0.14.0 build 1 build 2 build 3 build 4 build 5 build 6 build 7\nv0.14.1 v0.14.2 v0.14.3\n0.15\nFriendly Update\nv0.15.0\nRealms build 1 build 2 build 4\nbuild 1 build 2 build 3\nv0.15.1 build 1\nv0.15.2 v0.15.3 v0.15.4 v0.15.6 v0.15.7 v0.15.8 v0.15.9 v0.15.10\n0.16\nBoss Update\nv0.16.0 build 1 build 2 build 3 build 4 build 5\nv0.16.1 v0.16.2", "Version history Development versions", "Demo", "v0.1.0 v0.1.1 j v0.1.2 j v0.1.3 j", "v0.2.0 j v0.2.1 2 v0.2.2", "v0.3.0 v0.3.2 v0.3.3", "v0.4.0 j rev 2 rev 3", "v0.5.0 j", "v0.6.0 v0.6.1", "v0.7.0 v0.6.2\nv0.7.1 v0.7.2 v0.7.3 v0.7.4 v0.7.5 v0.7.6", "v0.6.2", "v0.8.0 build 1 build 2 build 3 build 4 build 5 build 6 build 7 build 8\nv0.8.1 v0.8.2", "build 1 build 2 build 3 build 4 build 5 build 6 build 7 build 8", "v0.9.0 build 1 build 2 build 3 build 4 build 5 build 6 build 7 build 8 build 9 (RC1) build 10 (RC2) build 11 (RC3) build 12 (RC4)\nv0.9.1 v0.9.2 v0.9.3 v0.9.4 v0.9.5", "build 1 build 2 build 3 build 4 build 5 build 6 build 7 build 8 build 9 (RC1) build 10 (RC2) build 11 (RC3) build 12 (RC4)", "v0.10.0 build 1 build 2 build 3 build 4 build 5 build 6 build 7 build 8 build 9\nv0.10.1 v0.10.2 v0.10.3 v0.10.4 v0.10.5", "build 1 build 2 build 3 build 4 build 5 build 6 build 7 build 8 build 9", "v0.11.0 build 1 build 2 build 3 build 4 build 5 build 6 build 7 build 8 build 9 build 10 build 11 build 12 build 13 build 14 (RC)\nv0.11.1 v0.11.2", "build 1 build 2 build 3 build 4 build 5 build 6 build 7 build 8 build 9 build 10 build 11 build 12 build 13 build 14 (RC)", "v0.12.0 v0.12.0.1\nv0.12.1 build 1 build 2 build 3 build 4 build 5 build 6 build 7 build 8 build 9 build 10 build 11 build 12 build 13\nv0.12.2 v0.12.3", "build 1 build 2 build 3 build 4 build 5 build 6 build 7 build 8 build 9 build 10 build 11 build 12 build 13", "v0.13.0 build 1 build 2 build 3 build 4 build 5\nv0.13.1 v0.13.2", "build 1 build 2 build 3 build 4 build 5", "v0.14.0 build 1 build 2 build 3 build 4 build 5 build 6 build 7\nv0.14.1 v0.14.2 v0.14.3", "build 1 build 2 build 3 build 4 build 5 build 6 build 7", "v0.15.0\nRealms build 1 build 2 build 4\nbuild 1 build 2 build 3\nv0.15.1 build 1\nv0.15.2 v0.15.3 v0.15.4 v0.15.6 v0.15.7 v0.15.8 v0.15.9 v0.15.10", "Realms build 1 build 2 build 4\nbuild 1 build 2 build 3", "build 1 build 2 build 4", "build 1", "v0.16.0 build 1 build 2 build 3 build 4 build 5\nv0.16.1 v0.16.2", "build 1 build 2 build 3 build 4 build 5", "[show]\nFull Release"], "bboxes": [[378.046875, 5877.34375, 547, 25], [378.046875, 5903.84375, 547, 25], [378.046875, 5930.34375, 547, 25], [205.046875, 5956.84375, 720, 922], [205.046875, 5985.796875, 720, 25], [330.046875, 6012.296875, 595, 25], [330.046875, 6038.796875, 595, 25], [330.046875, 6065.296875, 595, 25], [330.046875, 6091.796875, 595, 25], [330.046875, 6118.296875, 595, 25], [330.046875, 6144.796875, 595, 25], [330.046875, 6171.296875, 595, 25], [330.046875, 6197.796875, 595, 51], [395.046875, 6197.796875, 530, 25], [330.046875, 6250.796875, 595, 51], [398.046875, 6250.796875, 527, 25], [330.046875, 6303.796875, 595, 76], [395.046875, 6303.796875, 530, 49], [330.046875, 6381.296875, 595, 51], [404.046875, 6381.296875, 521, 25], [330.046875, 6434.296875, 595, 76], [401.046875, 6434.296875, 524, 49], [330.046875, 6511.796875, 595, 102], [399.046875, 6538.296875, 526, 49], [330.046875, 6615.796875, 595, 51], [403.046875, 6615.796875, 522, 25], [330.046875, 6668.796875, 595, 51], [404.046875, 6668.796875, 521, 25], [330.046875, 6721.796875, 595, 104], [403.046875, 6721.796875, 522, 51], [476.046875, 6721.796875, 449, 25], [403.046875, 6774.796875, 522, 25], [330.046875, 6827.796875, 595, 51], [403.046875, 6827.796875, 522, 25], [205.046875, 6880.796875, 720, 27]]}}, {"bbox": [203.046875, 5954.84375, 724, 926], "headers": {"text": ["[hide]\nAlpha", "Pre-release", "0.1", "0.2", "0.3", "0.4", "0.5", "0.6", "0.7", "v0.7.0", "0.8", "v0.8.0", "0.9", "v0.9.0", "0.10", "v0.10.0", "0.11", "v0.11.0", "0.12", "v0.12.1", "0.13", "v0.13.0", "0.14\nOverworld Update", "v0.14.0", "0.15\nFriendly Update", "v0.15.0", "Realms", "v0.15.1", "0.16\nBoss Update", "v0.16.0"], "bboxes": [[205.046875, 5956.84375, 720, 27], [205.046875, 6012.296875, 123, 25], [205.046875, 6038.796875, 123, 25], [205.046875, 6065.296875, 123, 25], [205.046875, 6091.796875, 123, 25], [205.046875, 6118.296875, 123, 25], [205.046875, 6144.796875, 123, 25], [205.046875, 6171.296875, 123, 25], [205.046875, 6197.796875, 123, 51], [330.046875, 6197.796875, 63, 25], [205.046875, 6250.796875, 123, 51], [330.046875, 6250.796875, 66, 25], [205.046875, 6303.796875, 123, 76], [330.046875, 6303.796875, 63, 49], [205.046875, 6381.296875, 123, 51], [330.046875, 6381.296875, 72, 25], [205.046875, 6434.296875, 123, 76], [330.046875, 6434.296875, 69, 49], [205.046875, 6511.796875, 123, 102], [330.046875, 6538.296875, 67, 49], [205.046875, 6615.796875, 123, 51], [330.046875, 6615.796875, 71, 25], [205.046875, 6668.796875, 123, 51], [330.046875, 6668.796875, 72, 25], [205.046875, 6721.796875, 123, 104], [330.046875, 6721.796875, 71, 51], [403.046875, 6721.796875, 71, 25], [330.046875, 6774.796875, 71, 25], [205.046875, 6827.796875, 123, 51], [330.046875, 6827.796875, 71, 25]]}, "cells": {"text": ["Version history Development versions", "Demo", "v0.1.0 v0.1.1 j v0.1.2 j v0.1.3 j", "v0.2.0 j v0.2.1 2 v0.2.2", "v0.3.0 v0.3.2 v0.3.3", "v0.4.0 j rev 2 rev 3", "v0.5.0 j", "v0.6.0 v0.6.1", "v0.7.0 v0.6.2\nv0.7.1 v0.7.2 v0.7.3 v0.7.4 v0.7.5 v0.7.6", "v0.6.2", "v0.8.0 build 1 build 2 build 3 build 4 build 5 build 6 build 7 build 8\nv0.8.1 v0.8.2", "build 1 build 2 build 3 build 4 build 5 build 6 build 7 build 8", "v0.9.0 build 1 build 2 build 3 build 4 build 5 build 6 build 7 build 8 build 9 (RC1) build 10 (RC2) build 11 (RC3) build 12 (RC4)\nv0.9.1 v0.9.2 v0.9.3 v0.9.4 v0.9.5", "build 1 build 2 build 3 build 4 build 5 build 6 build 7 build 8 build 9 (RC1) build 10 (RC2) build 11 (RC3) build 12 (RC4)", "v0.10.0 build 1 build 2 build 3 build 4 build 5 build 6 build 7 build 8 build 9\nv0.10.1 v0.10.2 v0.10.3 v0.10.4 v0.10.5", "build 1 build 2 build 3 build 4 build 5 build 6 build 7 build 8 build 9", "v0.11.0 build 1 build 2 build 3 build 4 build 5 build 6 build 7 build 8 build 9 build 10 build 11 build 12 build 13 build 14 (RC)\nv0.11.1 v0.11.2", "build 1 build 2 build 3 build 4 build 5 build 6 build 7 build 8 build 9 build 10 build 11 build 12 build 13 build 14 (RC)", "v0.12.0 v0.12.0.1\nv0.12.1 build 1 build 2 build 3 build 4 build 5 build 6 build 7 build 8 build 9 build 10 build 11 build 12 build 13\nv0.12.2 v0.12.3", "build 1 build 2 build 3 build 4 build 5 build 6 build 7 build 8 build 9 build 10 build 11 build 12 build 13", "v0.13.0 build 1 build 2 build 3 build 4 build 5\nv0.13.1 v0.13.2", "build 1 build 2 build 3 build 4 build 5", "v0.14.0 build 1 build 2 build 3 build 4 build 5 build 6 build 7\nv0.14.1 v0.14.2 v0.14.3", "build 1 build 2 build 3 build 4 build 5 build 6 build 7", "v0.15.0\nRealms build 1 build 2 build 4\nbuild 1 build 2 build 3\nv0.15.1 build 1\nv0.15.2 v0.15.3 v0.15.4 v0.15.6 v0.15.7 v0.15.8 v0.15.9 v0.15.10", "Realms build 1 build 2 build 4\nbuild 1 build 2 build 3", "build 1 build 2 build 4", "build 1", "v0.16.0 build 1 build 2 build 3 build 4 build 5\nv0.16.1 v0.16.2", "build 1 build 2 build 3 build 4 build 5"], "bboxes": [[205.046875, 5985.796875, 720, 25], [330.046875, 6012.296875, 595, 25], [330.046875, 6038.796875, 595, 25], [330.046875, 6065.296875, 595, 25], [330.046875, 6091.796875, 595, 25], [330.046875, 6118.296875, 595, 25], [330.046875, 6144.796875, 595, 25], [330.046875, 6171.296875, 595, 25], [330.046875, 6197.796875, 595, 51], [395.046875, 6197.796875, 530, 25], [330.046875, 6250.796875, 595, 51], [398.046875, 6250.796875, 527, 25], [330.046875, 6303.796875, 595, 76], [395.046875, 6303.796875, 530, 49], [330.046875, 6381.296875, 595, 51], [404.046875, 6381.296875, 521, 25], [330.046875, 6434.296875, 595, 76], [401.046875, 6434.296875, 524, 49], [330.046875, 6511.796875, 595, 102], [399.046875, 6538.296875, 526, 49], [330.046875, 6615.796875, 595, 51], [403.046875, 6615.796875, 522, 25], [330.046875, 6668.796875, 595, 51], [404.046875, 6668.796875, 521, 25], [330.046875, 6721.796875, 595, 104], [403.046875, 6721.796875, 522, 51], [476.046875, 6721.796875, 449, 25], [403.046875, 6774.796875, 522, 25], [330.046875, 6827.796875, 595, 51], [403.046875, 6827.796875, 522, 25]]}}, {"bbox": [328.046875, 6195.796875, 599, 29], "headers": {"text": ["v0.7.0"], "bboxes": [[330.046875, 6197.796875, 63, 25]]}, "cells": {"text": ["v0.6.2"], "bboxes": [[395.046875, 6197.796875, 530, 25]]}}, {"bbox": [328.046875, 6248.796875, 599, 29], "headers": {"text": ["v0.8.0"], "bboxes": [[330.046875, 6250.796875, 66, 25]]}, "cells": {"text": ["build 1 build 2 build 3 build 4 build 5 build 6 build 7 build 8"], "bboxes": [[398.046875, 6250.796875, 527, 25]]}}, {"bbox": [328.046875, 6301.796875, 599, 53], "headers": {"text": ["v0.9.0"], "bboxes": [[330.046875, 6303.796875, 63, 49]]}, "cells": {"text": ["build 1 build 2 build 3 build 4 build 5 build 6 build 7 build 8 build 9 (RC1) build 10 (RC2) build 11 (RC3) build 12 (RC4)"], "bboxes": [[395.046875, 6303.796875, 530, 49]]}}, {"bbox": [328.046875, 6379.296875, 599, 29], "headers": {"text": ["v0.10.0"], "bboxes": [[330.046875, 6381.296875, 72, 25]]}, "cells": {"text": ["build 1 build 2 build 3 build 4 build 5 build 6 build 7 build 8 build 9"], "bboxes": [[404.046875, 6381.296875, 521, 25]]}}, {"bbox": [328.046875, 6432.296875, 599, 53], "headers": {"text": ["v0.11.0"], "bboxes": [[330.046875, 6434.296875, 69, 49]]}, "cells": {"text": ["build 1 build 2 build 3 build 4 build 5 build 6 build 7 build 8 build 9 build 10 build 11 build 12 build 13 build 14 (RC)"], "bboxes": [[401.046875, 6434.296875, 524, 49]]}}, {"bbox": [328.046875, 6536.296875, 599, 53], "headers": {"text": ["v0.12.1"], "bboxes": [[330.046875, 6538.296875, 67, 49]]}, "cells": {"text": ["build 1 build 2 build 3 build 4 build 5 build 6 build 7 build 8 build 9 build 10 build 11 build 12 build 13"], "bboxes": [[399.046875, 6538.296875, 526, 49]]}}, {"bbox": [328.046875, 6613.796875, 599, 29], "headers": {"text": ["v0.13.0"], "bboxes": [[330.046875, 6615.796875, 71, 25]]}, "cells": {"text": ["build 1 build 2 build 3 build 4 build 5"], "bboxes": [[403.046875, 6615.796875, 522, 25]]}}, {"bbox": [328.046875, 6666.796875, 599, 29], "headers": {"text": ["v0.14.0"], "bboxes": [[330.046875, 6668.796875, 72, 25]]}, "cells": {"text": ["build 1 build 2 build 3 build 4 build 5 build 6 build 7"], "bboxes": [[404.046875, 6668.796875, 521, 25]]}}, {"bbox": [328.046875, 6719.796875, 599, 82], "headers": {"text": ["v0.15.0", "Realms", "v0.15.1"], "bboxes": [[330.046875, 6721.796875, 71, 51], [403.046875, 6721.796875, 71, 25], [330.046875, 6774.796875, 71, 25]]}, "cells": {"text": ["Realms build 1 build 2 build 4\nbuild 1 build 2 build 3", "build 1 build 2 build 4", "build 1"], "bboxes": [[403.046875, 6721.796875, 522, 51], [476.046875, 6721.796875, 449, 25], [403.046875, 6774.796875, 522, 25]]}}, {"bbox": [401.046875, 6719.796875, 526, 29], "headers": {"text": ["Realms"], "bboxes": [[403.046875, 6721.796875, 71, 25]]}, "cells": {"text": ["build 1 build 2 build 4"], "bboxes": [[476.046875, 6721.796875, 449, 25]]}}, {"bbox": [328.046875, 6825.796875, 599, 29], "headers": {"text": ["v0.16.0"], "bboxes": [[330.046875, 6827.796875, 71, 25]]}, "cells": {"text": ["build 1 build 2 build 3 build 4 build 5"], "bboxes": [[403.046875, 6827.796875, 522, 25]]}}, {"bbox": [203.046875, 6878.796875, 724, 31], "headers": {"text": ["[show]\nFull Release"], "bboxes": [[205.046875, 6880.796875, 720, 27]]}, "cells": {"text": [], "bboxes": []}}], "images": [{"src": "https://static.wikia.nocookie.net/minecraft_gamepedia/images/a/a7/Heart.svg", "path": "images/Heart.png", "alt_text": "Heart", "caption": null, "bbox": [276.046875, 6069.65625, 16, 16]}], "sprites": [{"text": null, "bbox": [215.046875, 5906.84375, 16, 16]}, {"text": "Alpha", "bbox": [380.046875, 5908.203125, 16, 16]}, {"text": "Full Release", "bbox": [502.40625, 5906.84375, 16, 16]}, {"text": "Bedrock Edition", "bbox": [696.765625, 5906.84375, 16, 16]}, {"text": null, "bbox": [245.046875, 5933.34375, 16, 16]}, {"text": "Alpha", "bbox": [504.5, 5962.84375, 16, 16]}, {"text": "Version history", "bbox": [420.125, 5988.796875, 16, 16]}, {"text": "Development versions", "bbox": [546.484375, 5988.796875, 16, 16]}, {"text": null, "bbox": [218.046875, 6015.296875, 16, 16]}, {"text": null, "bbox": [279.046875, 6041.796875, 16, 16]}, {"text": null, "bbox": [276.046875, 6094.796875, 16, 16]}, {"text": null, "bbox": [275.046875, 6121.296875, 16, 16]}, {"text": null, "bbox": [276.046875, 6147.796875, 16, 16]}, {"text": null, "bbox": [276.046875, 6174.296875, 16, 16]}, {"text": null, "bbox": [277.046875, 6214.046875, 16, 16]}, {"text": null, "bbox": [275.046875, 6267.046875, 16, 16]}, {"text": null, "bbox": [277.046875, 6332.296875, 16, 16]}, {"text": null, "bbox": [269.046875, 6397.546875, 16, 16]}, {"text": null, "bbox": [272.046875, 6462.796875, 16, 16]}, {"text": null, "bbox": [270.046875, 6553.546875, 16, 16]}, {"text": null, "bbox": [270.046875, 6632.046875, 16, 16]}, {"text": null, "bbox": [269.046875, 6672.796875, 16, 16]}, {"text": null, "bbox": [270.046875, 6752.296875, 16, 16]}, {"text": null, "bbox": [270.046875, 6831.796875, 16, 16]}, {"text": "Full Release", "bbox": [481, 6884.796875, 16, 16]}], "texts": [{"text": "Pocket Edition v0.10.0 alpha/Development versions", "bbox": [202.046875, 353.890625, 593, 90]}, {"text": "Contents", "bbox": [764.9375, 528.140625, 81, 17]}, {"text": "v0.10.0 alpha build 1\nv0.10.0 alpha build 2\nv0.10.0 alpha build 3\nv0.10.0 alpha build 4\nv0.10.0 alpha build 5\nv0.10.0 alpha build 6\nv0.10.0 alpha build 7\nv0.10.0 alpha build 8\nv0.10.0 alpha build 9\nNotes and references", "bbox": [752.9375, 561.40625, 174, 303]}, {"text": "This is a list of Pocket Edition v0.10.0 alpha development versions.", "bbox": [202.046875, 488.390625, 726, 25]}, {"text": "v0.10.0 alpha build 1", "bbox": [202.046875, 536.890625, 530, 43]}, {"text": "v0.10.0 alpha build 1 is the first build version released for v0.10.0.", "bbox": [202.046875, 588.890625, 726, 24]}, {"text": "Additions", "bbox": [202.046875, 637.390625, 726, 23]}, {"text": "Upgraded the rendering system to use OpenGL ES 2.0 (coming from 1.1), using OpenGL 3.0 where available.\nPorted tinted lighting from Java Edition.\nPorted the round fog from Java Edition.\nSome performance increase on most devices.\nMesa biomes have gold at every elevation and can spawn mine shafts on the surface.\nAdded dust particles falling from unstable gravel and sand.\nAdded more wood types for fences and gates.\nAdded adjustable brightness (gamma) setting to adjust the darkness of dark terrain.\niOS: Added a 64-bit build for compatible iOS devices.", "bbox": [238.046875, 671.890625, 690, 294]}, {"text": "Changes", "bbox": [202.046875, 989.890625, 726, 22]}, {"text": "New double-sided lighting on entities and clouds that's more coherent with the terrain.\nEnabled mipmaps on Android devices supporting GLES 3.0.\nNew water shader.\nWater is now brownish in swamps.\nFaster rebuilding of chunks.\nAdded smooth lighting on water and smooth color transitions.\nHuge mushrooms now spawn in swamps.\nIgnore swipes from outside the screen so exiting fullscreen/activating Control Center doesn't turn the view.\nThe selection overlay on vines/tall grass now has the correct shape.\nAdded a selection overlay on Chests and Signs.\nThe error messages when a World can't be opened are now more informative about what happened.\nEnabled Day/night cycle in Creative.", "bbox": [238.046875, 1024.390625, 690, 294]}, {"text": "Fixes", "bbox": [202.046875, 1342.390625, 726, 23]}, {"text": "13 bugs fixed", "bbox": [202.046875, 1376.890625, 726, 24]}, {"text": "Fixed a crash when rendering Mob Spawners.\niOS: Fixed freezing when receiving a notification/showing the Control Center.\niOS: Fixed a crash/memory leak happening when showing the system keyboard - signs and the chat.\nAndroid: fixed a corruption and possible crash when switching apps.\nFixed the \"spawning in the air\" bug.\nFixed a crash when creating lava during world generation.\nWater now pushes things\nFixed a white artifact on torches held in hand.\nFixed holes appearing in the clouds.\nFixed a brown artifact appearing on the bottom of Minecarts.\nFixed a random crash in multiplayer.\nFixed a possible crash when selecting double chests.\nThe time of day is now more accurately synced in multiplayer.", "bbox": [238.046875, 1425.390625, 690, 319]}, {"text": "v0.10.0 alpha build 2", "bbox": [202.046875, 1767.890625, 726, 43]}, {"text": "v0.10.0 alpha build 2 is the second build version released for v0.10.0.", "bbox": [202.046875, 1819.890625, 726, 24]}, {"text": "Changes", "bbox": [202.046875, 1868.390625, 726, 23]}, {"text": "Added smooth lighting back on leaves.\nSmoother depth transitions between swamps and normal water.\nThe \"round fog\" is now actually round.", "bbox": [238.046875, 1902.890625, 690, 73]}, {"text": "Fixes", "bbox": [202.046875, 2000.390625, 726, 23]}, {"text": "28 bugs fixed", "bbox": [202.046875, 2034.890625, 726, 24]}, {"text": "Added back the cross-hair when using Split Controls or the bow.\nFixed a lot of graphical issues when using Fancy on some old GPUs (PowerVR SGX535, SGX531, SGX540)\nFixed a crash when rendering minecarts.\nFixed a random crash when starting some worlds.\nFixed a crash when emitting particles.\nFixed disappearing GUI and weird mob bodies when having certain items on screen.\nFixed missing sides on slabs.\nFixed signs text showing through walls.\nFixed items having incorrect lighting.\nFixed items blinking white when next to a blinking TNT.\nItems no longer push you when falling.\nFixed an issue with 3rd person camera not raycasting through non-solid blocks.\nFixed arrows getting stuck on non-solid blocks.\nFixed falling tiles getting stuck on torches.\nFixed mineshafts spawning a ton of wooden platforms if discovered at night.\nFixed mushrooms appearing in deserts at night.\nFixed black lines on torches.\nMooshrooms now consume bowls when \"milked\".\nFixed a possible crash when falling under the world.\nBed undersides now have the correct texture.\nFixed Mob Spawner particles.\nFixed damage bars in inventories.\nWater in dark places doesn't have bright borders anymore.\nFixed water transparency under lily pads in swamps.\nGlass blocks don't have flickering faces between each other anymore.\nFixed colors of vines.\nBaby animals are now able to swim without sinking.\nFixed weird water colors when placing blocks on deep water.", "bbox": [238.046875, 2083.390625, 690, 686]}, {"text": "v0.10.0 alpha build 3", "bbox": [202.046875, 2787.390625, 726, 43]}, {"text": "v0.10.0 alpha build 3 is the third build version released for v0.10.0.", "bbox": [202.046875, 2839.390625, 726, 25]}, {"text": "Fixes", "bbox": [202.046875, 2887.890625, 726, 22]}, {"text": "5 bugs fixed", "bbox": [202.046875, 2922.390625, 726, 25]}, {"text": "The game doesn't get stuck on a black screen anymore on devices where it happened.\nThe player won't spawn anymore in the air or under bedrock.\nFixed a graphics corruption/crash happening when starting the game with Fancy OFF and turning it on.\nFixed flickering terrain and water in the distance on some devices.\nThe game doesn't freeze anymore when going to sleep.", "bbox": [238.046875, 2970.890625, 690, 122]}, {"text": "v0.10.0 alpha build 4", "bbox": [202.046875, 3111.390625, 726, 43]}, {"text": "v0.10.0 alpha build 4 is the fourth build version released for v0.10.0.", "bbox": [202.046875, 3163.390625, 726, 25]}, {"text": "Changes", "bbox": [202.046875, 3211.890625, 726, 22]}, {"text": "Glass walls have again only one side as in PC\nThe game now limits its CPU usage when in the background", "bbox": [238.046875, 3246.390625, 690, 49]}, {"text": "Fixes", "bbox": [202.046875, 3319.390625, 726, 23]}, {"text": "12 bugs fixed", "bbox": [202.046875, 3353.890625, 726, 24]}, {"text": "Fixed all black screen issues\nFixed missing stencil shadows on many devices\nRemoved black lines from torches and flowers on PowerVR devices\nFixed excessively close underwater fog with Fancy disabled\nSlope rails now have a correct hitbox\nFixed the number of dyes obtained from flowers and bones\nFixed spawning in leaves\nFixed a crash/corruption happening on app switch/reset\nFixed a biggish memory leak on world creation\nNow showing shadows on alpha tested tiles (glass, leaves)\nChickens don't have a black artifact under their head anymore\nThe brightness of the player in the armor inventory doesn't follow the in-world brightness anymore", "bbox": [238.046875, 3402.390625, 690, 294]}, {"text": "v0.10.0 alpha build 5", "bbox": [202.046875, 3714.390625, 726, 43]}, {"text": "v0.10.0 alpha build 5 is the fifth build version released for v0.10.0.", "bbox": [202.046875, 3766.390625, 726, 25]}, {"text": "Fixes", "bbox": [202.046875, 3814.890625, 726, 22]}, {"text": "9 bugs fixed", "bbox": [202.046875, 3849.390625, 726, 25]}, {"text": "Fixed a crash or graphics corruption when underwater\nFixed black screen on startup on yet more devices\nFixed black lines on the sides of doors\nReenabled OpenGLES 3 and mipmaps\nPossibly fixed some depth precision issues\nChat messages are now cleared when switching worlds\nThe game doesn't forget the settings change if quitting before exiting the options screen now\nFixed sensitivity lowering itself automatically\nDestroying a door by removing the underlying block now correctly yields a door item", "bbox": [238.046875, 3897.890625, 690, 220]}, {"text": "v0.10.0 alpha build 6", "bbox": [202.046875, 4136.390625, 726, 43]}, {"text": "v0.10.0 alpha build 6 is the sixth build version released for v0.10.0.", "bbox": [202.046875, 4188.390625, 726, 25]}, {"text": "Changes", "bbox": [202.046875, 4236.890625, 726, 22]}, {"text": "Walking animations are generally faster and have been tweaked per-animal.\nBetter fog on clouds, starting farther away and following the sky color.", "bbox": [238.046875, 4271.390625, 690, 49]}, {"text": "Fixes", "bbox": [202.046875, 4344.390625, 726, 23]}, {"text": "9 bugs fixed", "bbox": [202.046875, 4378.890625, 726, 24]}, {"text": "Chunks shouldn't fail anymore to be saved.\nFixed (again) the black screen problem on Android.\nFixed a possible crash on clients when the server quits the game.\nFixed growing crops not being saved.\nFixed empty chests and mob spawners found in mineshafts and strongholds.\nJoining a world as a client doesn't reset the spawn position to the log-in position anymore.\nMobs don't disappear anymore on clients if the client selects \"Peaceful\" difficulty.\nClients on \"Peaceful\" don't auto-heal anymore if playing on a \"Normal\" difficulty server.\nThe underwater fog now has the correct color in swamps.", "bbox": [238.046875, 4427.390625, 690, 221]}, {"text": "v0.10.0 alpha build 7", "bbox": [202.046875, 4665.890625, 726, 43]}, {"text": "v0.10.0 alpha build 7 is the seventh build version released for v0.10.0.", "bbox": [202.046875, 4717.890625, 726, 24]}, {"text": "Changes", "bbox": [202.046875, 4766.390625, 726, 23]}, {"text": "The clouds and the terrain are now tinted red during sunset.\nModders can now use shader version 300 if they wish to.\nPossibly made text rendering (especially non-ASCII) much faster.\nAdded back water sounds.", "bbox": [238.046875, 4800.890625, 690, 98]}, {"text": "Fixes", "bbox": [202.046875, 4922.890625, 726, 22]}, {"text": "4 bugs fixed", "bbox": [202.046875, 4957.390625, 726, 25]}, {"text": "Fixed an issue with server discovery.\n(Android) Fixed audio remaining muted after switching apps.\nCan sleep again when connecting to a server.\nThe player is now rotated correctly when sleeping.", "bbox": [238.046875, 5005.890625, 690, 98]}, {"text": "v0.10.0 alpha build 8", "bbox": [202.046875, 5121.890625, 726, 43]}, {"text": "v0.10.0 alpha build 8 is the eighth build version released for v0.10.0.", "bbox": [202.046875, 5173.890625, 726, 24]}, {"text": "Fixes", "bbox": [202.046875, 5222.390625, 726, 23]}, {"text": "1 bug fixed", "bbox": [202.046875, 5256.890625, 726, 24]}, {"text": "Fixed all characters being broken.", "bbox": [238.046875, 5305.390625, 690, 25]}, {"text": "v0.10.0 alpha build 9", "bbox": [202.046875, 5347.890625, 726, 43]}, {"text": "v0.10.0 alpha build 9 (RC1) is the ninth and final build version and first and only release candidate for v0.10.0, as well as the final build version released in 2014.", "bbox": [202.046875, 5399.890625, 726, 49]}, {"text": "Changes", "bbox": [202.046875, 5472.890625, 726, 22]}, {"text": "Beds are now easily placed on replaceable tiles like tallgrass", "bbox": [238.046875, 5507.390625, 690, 25]}, {"text": "Fixes", "bbox": [202.046875, 5555.890625, 726, 22]}, {"text": "5 bugs fixed", "bbox": [202.046875, 5590.390625, 726, 25]}, {"text": "Fixed number of blocks or items not showing up in toolbar and item panes\nFixed crash when shutting down server while client has chest/furnace open\nFixed entities in multiplayer. They should now work as expected\nDoor is now correctly updated (when opened/closed) on clients\nAdded back the opening top animation in chests", "bbox": [238.046875, 5638.890625, 690, 122]}, {"text": "Notes and references", "bbox": [202.046875, 5779.390625, 726, 43]}]}