{"metadata": {"url": "https://minecraft.fandom.com/wiki/Amethyst_Cluster/BS", "title": "Amethyst_Cluster/BS", "time": "17/04/2022 01:38:28"}, "tables": [{"bbox": [202.046875, 510.5, 725, 265], "headers": {"text": ["Name", "Default value", "Allowed values", "Description", "facing", "waterlogged"], "bboxes": [[202.546875, 511, 101, 55], [303.734375, 511, 99, 55], [402.90625, 511, 110, 55], [513.078125, 511, 414, 55], [202.546875, 566.59375, 101, 153], [202.546875, 720.1875, 101, 55]]}, "cells": {"text": ["up", "up\ndown\nnorth\nsouth\neast\nwest", "The direction that the amethyst is facing, determined by its anchoring.", "false", "true\nfalse", "Whether or not the amethyst is located inside of water."], "bboxes": [[303.734375, 566.59375, 99, 153], [402.90625, 566.59375, 110, 153], [513.078125, 566.59375, 414, 153], [303.734375, 720.1875, 99, 55], [402.90625, 720.1875, 110, 55], [513.078125, 720.1875, 414, 55]]}}, {"bbox": [202.046875, 852.78125, 725, 283], "headers": {"text": ["Name", "Metadata Bits", "Default value", "Allowed values", "Values for\nMetadata Bits", "Description", "facing_direction"], "bboxes": [[202.546875, 853.28125, 130, 55], [332.734375, 853.28125, 97, 55], [430.390625, 853.28125, 88, 55], [517.65625, 853.28125, 96, 55], [613.546875, 853.28125, 114, 55], [728.15625, 853.28125, 199, 55], [202.546875, 908.875, 130, 226]]}, "cells": {"text": ["Not Supported", "0", "0\n1\n2\n3\n4\n5", "Unsupported", "The direction that the amethyst is facing.\n0: down\n1: up\n2: north\n3: south\n4: west\n5: east"], "bboxes": [[332.734375, 908.875, 97, 226], [430.390625, 908.875, 88, 226], [517.65625, 908.875, 96, 226], [613.546875, 908.875, 114, 226], [728.15625, 908.875, 199, 226]]}}], "images": [], "sprites": [], "texts": [{"text": "Amethyst Cluster/BS", "bbox": [202.046875, 358.5, 593, 45]}, {"text": "Java Edition:", "bbox": [202.046875, 448, 726, 25]}, {"text": "Bedrock Edition:", "bbox": [202.046875, 790.28125, 726, 25]}]}