{"metadata": {"url": "https://minecraft.fandom.com/wiki/Commands/move", "title": "Commands/move", "time": "16/04/2022 23:22:12"}, "tables": [{"bbox": [624.9375, 608.234375, 300, 117], "headers": {"text": ["Visibility", "Permission level\nrequired", "Restrictions"], "bboxes": [[625.9375, 609.234375, 209, 30], [625.9375, 640.265625, 209, 52], [625.9375, 693.328125, 209, 30]]}, "cells": {"text": ["Hidden", "0", "None"], "bboxes": [[835.734375, 609.234375, 88, 30], [835.734375, 640.265625, 88, 52], [835.734375, 693.328125, 88, 30]]}}, {"bbox": [202.046875, 1457.28125, 140, 63], "headers": {"text": ["Education Edition", "?"], "bboxes": [[202.546875, 1457.78125, 139, 31], [202.546875, 1488.875, 21, 31]]}, "cells": {"text": ["Added /move."], "bboxes": [[223.765625, 1488.875, 118, 31]]}}], "images": [{"src": "https://static.wikia.nocookie.net/minecraft_gamepedia/images/3/35/Information_icon.svg", "path": "images/Information icon.png", "alt_text": "Information icon", "caption": null, "bbox": [260.53125, 514.171875, 32, 32]}], "sprites": [{"text": null, "bbox": [260.53125, 459.984375, 32, 32]}], "texts": [{"text": "Commands/move", "bbox": [202.046875, 353.890625, 593, 45]}, {"text": "Moves an Agent in a specified direction.", "bbox": [202.046875, 566.765625, 726, 25]}, {"text": "Contents", "bbox": [215.046875, 631.015625, 81, 17]}, {"text": "1 Syntax\n2 Arguments\n3 Result\n4 History", "bbox": [203.046875, 664.28125, 145, 132]}, {"text": "Syntax", "bbox": [202.046875, 821.28125, 726, 43]}, {"text": "move <direction: string>", "bbox": [202.046875, 873.28125, 726, 24]}, {"text": "Arguments", "bbox": [202.046875, 921.78125, 726, 43]}, {"text": "direction: string", "bbox": [202.046875, 973.78125, 726, 25]}, {"text": "Specifies the direction of where the Agent is to move.\nMust be one of:\nforward to move the Agent forward.\nback to move the Agent backward.\nleft to move the Agent leftward.\nright to move the Agent rightward.\nup to move the Agent upward.\ndown to move the Agent downward.", "bbox": [202.046875, 1022.28125, 726, 202]}, {"text": "Result", "bbox": [202.046875, 1242.28125, 726, 43]}, {"text": "Fails if the specified direction is blocked by a block.", "bbox": [202.046875, 1294.28125, 726, 24]}, {"text": "On success, the Agent is moved in the direction specified by one block.", "bbox": [202.046875, 1342.78125, 726, 25]}, {"text": "History", "bbox": [202.046875, 1391.28125, 726, 43]}, {"text": "Commands[show] [edit]", "bbox": [205.046875, 1551.46875, 720, 25]}]}